Workbook
Name quarterly_data: quarterly!$A$1:$J$227

Sheet data
A1: quarter_start | B1: quarter_end | C1: rtwi | D1: tot | E1: wui_au | F1: wui_au_sm | G1: us_rgdp | H1: au_rgdp | I1: au_inf_trim | J1: au_cpi | K1: ntwi | L1: aud_usd | M1: comm_price | N1: comm_price_bulk | O1: iron_ore | P1: coal | Q1: brent_crude | R1: natural_gas | S1: cash_rate | T1: fed_funds | U1: au_us_policy_rate | V1: au_2yr_yield | W1: us_2yr_yield | X1: au_us_2yr | Y1: au_10yr_yield | Z1: us_10yr_yield | AA1: au_us_10yr | AB1: vix | AC1: gepu | AD1: au_epu | AE1: gpr_global | AF1: gprt_global | AG1: gpra_global | AH1: gprc_au
A2: 25569 | B2: 25657 | C2: =IF(ISBLANK(VLOOKUP($A2,quarterly_data,MATCH(C$1,quarterly!$1:$1,FALSE),FALSE)),"NA",VLOOKUP($A2,quarterly_data,MATCH(C$1,quarterly!$1:$1,FALSE),FALSE)) -> NA | D2: =IF(ISBLANK(VLOOKUP($A2,quarterly_data,MATCH(D$1,quarterly!$1:$1,FALSE),FALSE)),"NA",VLOOKUP($A2,quarterly_data,MATCH(D$1,quarterly!$1:$1,FALSE),FALSE)) -> NA | E2: =IF(ISBLANK(VLOOKUP($A2,quarterly_data,MATCH(E$1,quarterly!$1:$1,FALSE),FALSE)),"NA",VLOOKUP($A2,quarterly_data,MATCH(E$1,quarterly!$1:$1,FALSE),FALSE)) -> 0 | F2: =IF(ISBLANK(VLOOKUP($A2,quarterly_data,MATCH(F$1,quarterly!$1:$1,FALSE),FALSE)),"NA",VLOOKUP($A2,quarterly_data,MATCH(F$1,quarterly!$1:$1,FALSE),FALSE)) -> 0.0111744 | G2: =IF(ISBLANK(VLOOKUP($A2,quarterly_data,MATCH(G$1,quarterly!$1:$1,FALSE),FALSE)),"NA",VLOOKUP($A2,quarterly_data,MATCH(G$1,quarterly!$1:$1,FALSE),FALSE)) -> 5300.652 | H2: =IF(ISBLANK(VLOOKUP($A2,quarterly_data,MATCH(H$1,quarterly!$1:$1,FALSE),FALSE)),"NA",VLOOKUP($A2,quarterly_data,MATCH(H$1,quarterly!$1:$1,FALSE),FALSE)) -> 136260 | I2: =IF(ISBLANK(VLOOKUP($A2,quarterly_data,MATCH(I$1,quarterly!$1:$1,FALSE),FALSE)),"NA",VLOOKUP($A2,quarterly_data,MATCH(I$1,quarterly!$1:$1,FALSE),FALSE)) -> NA | J2: =IF(ISBLANK(VLOOKUP($A2,quarterly_data,MATCH(J$1,quarterly!$1:$1,FALSE),FALSE)),"NA",VLOOKUP($A2,quarterly_data,MATCH(J$1,quarterly!$1:$1,FALSE),FALSE)) -> 6.69 | K2: =IF(COUNTIFS(monthly!C:C,"",monthly!$A:$A,">="&$A2,monthly!$B:$B,"<="&$B2)>0,"NA",AVERAGEIFS(monthly!C:C,monthly!$A:$A,">="&$A2,monthly!$B:$B,"<="&$B2)) -> NA | L2: =IF(COUNTIFS(monthly!D:D,"",monthly!$A:$A,">="&$A2,monthly!$B:$B,"<="&$B2)>0,"NA",AVERAGEIFS(monthly!D:D,monthly!$A:$A,">="&$A2,monthly!$B:$B,"<="&$B2)) -> 1.1197 | M2: =IF(COUNTIFS(monthly!E:E,"",monthly!$A:$A,">="&$A2,monthly!$B:$B,"<="&$B2)>0,"NA",AVERAGEIFS(monthly!E:E,monthly!$A:$A,">="&$A2,monthly!$B:$B,"<="&$B2)) -> NA | N2: =IF(COUNTIFS(monthly!F:F,"",monthly!$A:$A,">="&$A2,monthly!$B:$B,"<="&$B2)>0,"NA",AVERAGEIFS(monthly!F:F,monthly!$A:$A,">="&$A2,monthly!$B:$B,"<="&$B2)) -> NA | O2: =IF(COUNTIFS(monthly!G:G,"",monthly!$A:$A,">="&$A2,monthly!$B:$B,"<="&$B2)>0,"NA",AVERAGEIFS(monthly!G:G,monthly!$A:$A,">="&$A2,monthly!$B:$B,"<="&$B2)) -> 9.8 | P2: =IF(COUNTIFS(monthly!H:H,"",monthly!$A:$A,">="&$A2,monthly!$B:$B,"<="&$B2)>0,"NA",AVERAGEIFS(monthly!H:H,monthly!$A:$A,">="&$A2,monthly!$B:$B,"<="&$B2)) -> 7.8 | Q2: =IF(COUNTIFS(monthly!I:I,"",monthly!$A:$A,">="&$A2,monthly!$B:$B,"<="&$B2)>0,"NA",AVERAGEIFS(monthly!I:I,monthly!$A:$A,">="&$A2,monthly!$B:$B,"<="&$B2)) -> 1.2 | R2: =IF(COUNTIFS(monthly!J:J,"",monthly!$A:$A,">="&$A2,monthly!$B:$B,"<="&$B2)>0,"NA",AVERAGEIFS(monthly!J:J,monthly!$A:$A,">="&$A2,monthly!$B:$B,"<="&$B2)) -> NA | S2: =IF(COUNTIFS(monthly!K:K,"",monthly!$A:$A,">="&$A2,monthly!$B:$B,"<="&$B2)>0,"NA",AVERAGEIFS(monthly!K:K,monthly!$A:$A,">="&$A2,monthly!$B:$B,"<="&$B2)) -> NA | T2: =IF(COUNTIFS(monthly!L:L,"",monthly!$A:$A,">="&$A2,monthly!$B:$B,"<="&$B2)>0,"NA",AVERAGEIFS(monthly!L:L,monthly!$A:$A,">="&$A2,monthly!$B:$B,"<="&$B2)) -> 8.9774942 | U2: =IF(COUNTIFS(monthly!M:M,"",monthly!$A:$A,">="&$A2,monthly!$B:$B,"<="&$B2)>0,"NA",AVERAGEIFS(monthly!M:M,monthly!$A:$A,">="&$A2,monthly!$B:$B,"<="&$B2)) -> NA | V2: =IF(COUNTIFS(monthly!N:N,"",monthly!$A:$A,">="&$A2,monthly!$B:$B,"<="&$B2)>0,"NA",AVERAGEIFS(monthly!N:N,monthly!$A:$A,">="&$A2,monthly!$B:$B,"<="&$B2)) -> NA | W2: =IF(COUNTIFS(monthly!O:O,"",monthly!$A:$A,">="&$A2,monthly!$B:$B,"<="&$B2)>0,"NA",AVERAGEIFS(monthly!O:O,monthly!$A:$A,">="&$A2,monthly!$B:$B,"<="&$B2)) -> NA | X2: =IF(COUNTIFS(monthly!P:P,"",monthly!$A:$A,">="&$A2,monthly!$B:$B,"<="&$B2)>0,"NA",AVERAGEIFS(monthly!P:P,monthly!$A:$A,">="&$A2,monthly!$B:$B,"<="&$B2)) -> NA | Y2: =IF(COUNTIFS(monthly!Q:Q,"",monthly!$A:$A,">="&$A2,monthly!$B:$B,"<="&$B2)>0,"NA",AVERAGEIFS(monthly!Q:Q,monthly!$A:$A,">="&$A2,monthly!$B:$B,"<="&$B2)) -> 5.955 | Z2: =IF(COUNTIFS(monthly!R:R,"",monthly!$A:$A,">="&$A2,monthly!$B:$B,"<="&$B2)>0,"NA",AVERAGEIFS(monthly!R:R,monthly!$A:$A,">="&$A2,monthly!$B:$B,"<="&$B2)) -> 7.5165476 | AA2: =IF(COUNTIFS(monthly!S:S,"",monthly!$A:$A,">="&$A2,monthly!$B:$B,"<="&$B2)>0,"NA",AVERAGEIFS(monthly!S:S,monthly!$A:$A,">="&$A2,monthly!$B:$B,"<="&$B2)) -> -1.5615476 | AB2: =IF(COUNTIFS(monthly!T:T,"",monthly!$A:$A,">="&$A2,monthly!$B:$B,"<="&$B2)>0,"NA",AVERAGEIFS(monthly!T:T,monthly!$A:$A,">="&$A2,monthly!$B:$B,"<="&$B2)) -> NA | AC2: =IF(COUNTIFS(monthly!U:U,"",monthly!$A:$A,">="&$A2,monthly!$B:$B,"<="&$B2)>0,"NA",AVERAGEIFS(monthly!U:U,monthly!$A:$A,">="&$A2,monthly!$B:$B,"<="&$B2)) -> NA | AD2: =IF(COUNTIFS(monthly!V:V,"",monthly!$A:$A,">="&$A2,monthly!$B:$B,"<="&$B2)>0,"NA",AVERAGEIFS(monthly!V:V,monthly!$A:$A,">="&$A2,monthly!$B:$B,"<="&$B2)) -> NA | AE2: =IF(COUNTIFS(monthly!W:W,"",monthly!$A:$A,">="&$A2,monthly!$B:$B,"<="&$B2)>0,"NA",AVERAGEIFS(monthly!W:W,monthly!$A:$A,">="&$A2,monthly!$B:$B,"<="&$B2)) -> NA | AF2: =IF(COUNTIFS(monthly!X:X,"",monthly!$A:$A,">="&$A2,monthly!$B:$B,"<="&$B2)>0,"NA",AVERAGEIFS(monthly!X:X,monthly!$A:$A,">="&$A2,monthly!$B:$B,"<="&$B2)) -> NA | AG2: =IF(COUNTIFS(monthly!Y:Y,"",monthly!$A:$A,">="&$A2,monthly!$B:$B,"<="&$B2)>0,"NA",AVERAGEIFS(monthly!Y:Y,monthly!$A:$A,">="&$A2,monthly!$B:$B,"<="&$B2)) -> NA | AH2: =IF(COUNTIFS(monthly!Z:Z,"",monthly!$A:$A,">="&$A2,monthly!$B:$B,"<="&$B2)>0,"NA",AVERAGEIFS(monthly!Z:Z,monthly!$A:$A,">="&$A2,monthly!$B:$B,"<="&$B2)) -> NA
A3: 25659 | B3: 25749 | C3: =IF(ISBLANK(VLOOKUP($A3,quarterly_data,MATCH(C$1,quarterly!$1:$1,FALSE),FALSE)),"NA",VLOOKUP($A3,quarterly_data,MATCH(C$1,quarterly!$1:$1,FALSE),FALSE)) -> 146.45132 | D3: =IF(ISBLANK(VLOOKUP($A3,quarterly_data,MATCH(D$1,quarterly!$1:$1,FALSE),FALSE)),"NA",VLOOKUP($A3,quarterly_data,MATCH(D$1,quarterly!$1:$1,FALSE),FALSE)) -> 59.1 | E3: =IF(ISBLANK(VLOOKUP($A3,quarterly_data,MATCH(E$1,quarterly!$1:$1,FALSE),FALSE)),"NA",VLOOKUP($A3,quarterly_data,MATCH(E$1,quarterly!$1:$1,FALSE),FALSE)) -> 0.2192982 | F3: =IF(ISBLANK(VLOOKUP($A3,quarterly_data,MATCH(F$1,quarterly!$1:$1,FALSE),FALSE)),"NA",VLOOKUP($A3,quarterly_data,MATCH(F$1,quarterly!$1:$1,FALSE),FALSE)) -> 0.0438596 | G3: =IF(ISBLANK(VLOOKUP($A3,quarterly_data,MATCH(G$1,quarterly!$1:$1,FALSE),FALSE)),"NA",VLOOKUP($A3,quarterly_data,MATCH(G$1,quarterly!$1:$1,FALSE),FALSE)) -> 5308.164 | H3: =IF(ISBLANK(VLOOKUP($A3,quarterly_data,MATCH(H$1,quarterly!$1:$1,FALSE),FALSE)),"NA",VLOOKUP($A3,quarterly_data,MATCH(H$1,quarterly!$1:$1,FALSE),FALSE)) -> 139021 | I3: =IF(ISBLANK(VLOOKUP($A3,quarterly_data,MATCH(I$1,quarterly!$1:$1,FALSE),FALSE)),"NA",VLOOKUP($A3,quarterly_data,MATCH(I$1,quarterly!$1:$1,FALSE),FALSE)) -> NA | J3: =IF(ISBLANK(VLOOKUP($A3,quarterly_data,MATCH(J$1,quarterly!$1:$1,FALSE),FALSE)),"NA",VLOOKUP($A3,quarterly_data,MATCH(J$1,quarterly!$1:$1,FALSE),FALSE)) -> 6.77 | K3: =IF(COUNTIFS(monthly!C:C,"",monthly!$A:$A,">="&$A3,monthly!$B:$B,"<="&$B3)>0,"NA",AVERAGEIFS(monthly!C:C,monthly!$A:$A,">="&$A3,monthly!$B:$B,"<="&$B3)) -> NA | L3: =IF(COUNTIFS(monthly!D:D,"",monthly!$A:$A,">="&$A3,monthly!$B:$B,"<="&$B3)>0,"NA",AVERAGEIFS(monthly!D:D,monthly!$A:$A,">="&$A3,monthly!$B:$B,"<="&$B3)) -> 1.1183667 | M3: =IF(COUNTIFS(monthly!E:E,"",monthly!$A:$A,">="&$A3,monthly!$B:$B,"<="&$B3)>0,"NA",AVERAGEIFS(monthly!E:E,monthly!$A:$A,">="&$A3,monthly!$B:$B,"<="&$B3)) -> NA | N3: =IF(COUNTIFS(monthly!F:F,"",monthly!$A:$A,">="&$A3,monthly!$B:$B,"<="&$B3)>0,"NA",AVERAGEIFS(monthly!F:F,monthly!$A:$A,">="&$A3,monthly!$B:$B,"<="&$B3)) -> NA | O3: =IF(COUNTIFS(monthly!G:G,"",monthly!$A:$A,">="&$A3,monthly!$B:$B,"<="&$B3)>0,"NA",AVERAGEIFS(monthly!G:G,monthly!$A:$A,">="&$A3,monthly!$B:$B,"<="&$B3)) -> 9.8 | P3: =IF(COUNTIFS(monthly!H:H,"",monthly!$A:$A,">="&$A3,monthly!$B:$B,"<="&$B3)>0,"NA",AVERAGEIFS(monthly!H:H,monthly!$A:$A,">="&$A3,monthly!$B:$B,"<="&$B3)) -> 7.8 | Q3: =IF(COUNTIFS(monthly!I:I,"",monthly!$A:$A,">="&$A3,monthly!$B:$B,"<="&$B3)>0,"NA",AVERAGEIFS(monthly!I:I,monthly!$A:$A,">="&$A3,monthly!$B:$B,"<="&$B3)) -> 1.2 | R3: =IF(COUNTIFS(monthly!J:J,"",monthly!$A:$A,">="&$A3,monthly!$B:$B,"<="&$B3)>0,"NA",AVERAGEIFS(monthly!J:J,monthly!$A:$A,">="&$A3,monthly!$B:$B,"<="&$B3)) -> NA | S3: =IF(COUNTIFS(monthly!K:K,"",monthly!$A:$A,">="&$A3,monthly!$B:$B,"<="&$B3)>0,"NA",AVERAGEIFS(monthly!K:K,monthly!$A:$A,">="&$A3,monthly!$B:$B,"<="&$B3)) -> NA | T3: =IF(COUNTIFS(monthly!L:L,"",monthly!$A:$A,">="&$A3,monthly!$B:$B,"<="&$B3)>0,"NA",AVERAGEIFS(monthly!L:L,monthly!$A:$A,">="&$A3,monthly!$B:$B,"<="&$B3)) -> 7.882595 | U3: =IF(COUNTIFS(monthly!M:M,"",monthly!$A:$A,">="&$A3,monthly!$B:$B,"<="&$B3)>0,"NA",AVERAGEIFS(monthly!M:M,monthly!$A:$A,">="&$A3,monthly!$B:$B,"<="&$B3)) -> NA | V3: =IF(COUNTIFS(monthly!N:N,"",monthly!$A:$A,">="&$A3,monthly!$B:$B,"<="&$B3)>0,"NA",AVERAGEIFS(monthly!N:N,monthly!$A:$A,">="&$A3,monthly!$B:$B,"<="&$B3)) -> NA | W3: =IF(COUNTIFS(monthly!O:O,"",monthly!$A:$A,">="&$A3,monthly!$B:$B,"<="&$B3)>0,"NA",AVERAGEIFS(monthly!O:O,monthly!$A:$A,">="&$A3,monthly!$B:$B,"<="&$B3)) -> NA | X3: =IF(COUNTIFS(monthly!P:P,"",monthly!$A:$A,">="&$A3,monthly!$B:$B,"<="&$B3)>0,"NA",AVERAGEIFS(monthly!P:P,monthly!$A:$A,">="&$A3,monthly!$B:$B,"<="&$B3)) -> NA | Y3: =IF(COUNTIFS(monthly!Q:Q,"",monthly!$A:$A,">="&$A3,monthly!$B:$B,"<="&$B3)>0,"NA",AVERAGEIFS(monthly!Q:Q,monthly!$A:$A,">="&$A3,monthly!$B:$B,"<="&$B3)) -> 6.8833333 | Z3: =IF(COUNTIFS(monthly!R:R,"",monthly!$A:$A,">="&$A3,monthly!$B:$B,"<="&$B3)>0,"NA",AVERAGEIFS(monthly!R:R,monthly!$A:$A,">="&$A3,monthly!$B:$B,"<="&$B3)) -> 7.7129726 | AA3: =IF(COUNTIFS(monthly!S:S,"",monthly!$A:$A,">="&$A3,monthly!$B:$B,"<="&$B3)>0,"NA",AVERAGEIFS(monthly!S:S,monthly!$A:$A,">="&$A3,monthly!$B:$B,"<="&$B3)) -> -0.82963925 | AB3: =IF(COUNTIFS(monthly!T:T,"",monthly!$A:$A,">="&$A3,monthly!$B:$B,"<="&$B3)>0,"NA",AVERAGEIFS(monthly!T:T,monthly!$A:$A,">="&$A3,monthly!$B:$B,"<="&$B3)) -> NA | AC3: =IF(COUNTIFS(monthly!U:U,"",monthly!$A:$A,">="&$A3,monthly!$B:$B,"<="&$B3)>0,"NA",AVERAGEIFS(monthly!U:U,monthly!$A:$A,">="&$A3,monthly!$B:$B,"<="&$B3)) -> NA | AD3: =IF(COUNTIFS(monthly!V:V,"",monthly!$A:$A,">="&$A3,monthly!$B:$B,"<="&$B3)>0,"NA",AVERAGEIFS(monthly!V:V,monthly!$A:$A,">="&$A3,monthly!$B:$B,"<="&$B3)) -> NA | AE3: =IF(COUNTIFS(monthly!W:W,"",monthly!$A:$A,">="&$A3,monthly!$B:$B,"<="&$B3)>0,"NA",AVERAGEIFS(monthly!W:W,monthly!$A:$A,">="&$A3,monthly!$B:$B,"<="&$B3)) -> NA | AF3: =IF(COUNTIFS(monthly!X:X,"",monthly!$A:$A,">="&$A3,monthly!$B:$B,"<="&$B3)>0,"NA",AVERAGEIFS(monthly!X:X,monthly!$A:$A,">="&$A3,monthly!$B:$B,"<="&$B3)) -> NA | AG3: =IF(COUNTIFS(monthly!Y:Y,"",monthly!$A:$A,">="&$A3,monthly!$B:$B,"<="&$B3)>0,"NA",AVERAGEIFS(monthly!Y:Y,monthly!$A:$A,">="&$A3,monthly!$B:$B,"<="&$B3)) -> NA | AH3: =IF(COUNTIFS(monthly!Z:Z,"",monthly!$A:$A,">="&$A3,monthly!$B:$B,"<="&$B3)>0,"NA",AVERAGEIFS(monthly!Z:Z,monthly!$A:$A,">="&$A3,monthly!$B:$B,"<="&$B3)) -> NA
A4: 25750 | B4: 25841 | C4: =IF(ISBLANK(VLOOKUP($A4,quarterly_data,MATCH(C$1,quarterly!$1:$1,FALSE),FALSE)),"NA",VLOOKUP($A4,quarterly_data,MATCH(C$1,quarterly!$1:$1,FALSE),FALSE)) -> 144.54268 | D4: =IF(ISBLANK(VLOOKUP($A4,quarterly_data,MATCH(D$1,quarterly!$1:$1,FALSE),FALSE)),"NA",VLOOKUP($A4,quarterly_data,MATCH(D$1,quarterly!$1:$1,FALSE),FALSE)) -> 58.1 | E4: =IF(ISBLANK(VLOOKUP($A4,quarterly_data,MATCH(E$1,quarterly!$1:$1,FALSE),FALSE)),"NA",VLOOKUP($A4,quarterly_data,MATCH(E$1,quarterly!$1:$1,FALSE),FALSE)) -> 0 | F4: =IF(ISBLANK(VLOOKUP($A4,quarterly_data,MATCH(F$1,quarterly!$1:$1,FALSE),FALSE)),"NA",VLOOKUP($A4,quarterly_data,MATCH(F$1,quarterly!$1:$1,FALSE),FALSE)) -> 0.0219298 | G4: =IF(ISBLANK(VLOOKUP($A4,quarterly_data,MATCH(G$1,quarterly!$1:$1,FALSE),FALSE)),"NA",VLOOKUP($A4,quarterly_data,MATCH(G$1,quarterly!$1:$1,FALSE),FALSE)) -> 5357.077 | H4: =IF(ISBLANK(VLOOKUP($A4,quarterly_data,MATCH(H$1,quarterly!$1:$1,FALSE),FALSE)),"NA",VLOOKUP($A4,quarterly_data,MATCH(H$1,quarterly!$1:$1,FALSE),FALSE)) -> 138729 | I4: =IF(ISBLANK(VLOOKUP($A4,quarterly_data,MATCH(I$1,quarterly!$1:$1,FALSE),FALSE)),"NA",VLOOKUP($A4,quarterly_data,MATCH(I$1,quarterly!$1:$1,FALSE),FALSE)) -> NA | J4: =IF(ISBLANK(VLOOKUP($A4,quarterly_data,MATCH(J$1,quarterly!$1:$1,FALSE),FALSE)),"NA",VLOOKUP($A4,quarterly_data,MATCH(J$1,quarterly!$1:$1,FALSE),FALSE)) -> 6.8 | K4: =IF(COUNTIFS(monthly!C:C,"",monthly!$A:$A,">="&$A4,monthly!$B:$B,"<="&$B4)>0,"NA",AVERAGEIFS(monthly!C:C,monthly!$A:$A,">="&$A4,monthly!$B:$B,"<="&$B4)) -> 99.233333 | L4: =IF(COUNTIFS(monthly!D:D,"",monthly!$A:$A,">="&$A4,monthly!$B:$B,"<="&$B4)>0,"NA",AVERAGEIFS(monthly!D:D,monthly!$A:$A,">="&$A4,monthly!$B:$B,"<="&$B4)) -> 1.1117333 | M4: =IF(COUNTIFS(monthly!E:E,"",monthly!$A:$A,">="&$A4,monthly!$B:$B,"<="&$B4)>0,"NA",AVERAGEIFS(monthly!E:E,monthly!$A:$A,">="&$A4,monthly!$B:$B,"<="&$B4)) -> NA | N4: =IF(COUNTIFS(monthly!F:F,"",monthly!$A:$A,">="&$A4,monthly!$B:$B,"<="&$B4)>0,"NA",AVERAGEIFS(monthly!F:F,monthly!$A:$A,">="&$A4,monthly!$B:$B,"<="&$B4)) -> NA | O4: =IF(COUNTIFS(monthly!G:G,"",monthly!$A:$A,">="&$A4,monthly!$B:$B,"<="&$B4)>0,"NA",AVERAGEIFS(monthly!G:G,monthly!$A:$A,">="&$A4,monthly!$B:$B,"<="&$B4)) -> 9.8 | P4: =IF(COUNTIFS(monthly!H:H,"",monthly!$A:$A,">="&$A4,monthly!$B:$B,"<="&$B4)>0,"NA",AVERAGEIFS(monthly!H:H,monthly!$A:$A,">="&$A4,monthly!$B:$B,"<="&$B4)) -> 7.8 | Q4: =IF(COUNTIFS(monthly!I:I,"",monthly!$A:$A,">="&$A4,monthly!$B:$B,"<="&$B4)>0,"NA",AVERAGEIFS(monthly!I:I,monthly!$A:$A,">="&$A4,monthly!$B:$B,"<="&$B4)) -> 1.2 | R4: =IF(COUNTIFS(monthly!J:J,"",monthly!$A:$A,">="&$A4,monthly!$B:$B,"<="&$B4)>0,"NA",AVERAGEIFS(monthly!J:J,monthly!$A:$A,">="&$A4,monthly!$B:$B,"<="&$B4)) -> NA | S4: =IF(COUNTIFS(monthly!K:K,"",monthly!$A:$A,">="&$A4,monthly!$B:$B,"<="&$B4)>0,"NA",AVERAGEIFS(monthly!K:K,monthly!$A:$A,">="&$A4,monthly!$B:$B,"<="&$B4)) -> NA | T4: =IF(COUNTIFS(monthly!L:L,"",monthly!$A:$A,">="&$A4,monthly!$B:$B,"<="&$B4)>0,"NA",AVERAGEIFS(monthly!L:L,monthly!$A:$A,">="&$A4,monthly!$B:$B,"<="&$B4)) -> 6.7065556 | U4: =IF(COUNTIFS(monthly!M:M,"",monthly!$A:$A,">="&$A4,monthly!$B:$B,"<="&$B4)>0,"NA",AVERAGEIFS(monthly!M:M,monthly!$A:$A,">="&$A4,monthly!$B:$B,"<="&$B4)) -> NA | V4: =IF(COUNTIFS(monthly!N:N,"",monthly!$A:$A,">="&$A4,monthly!$B:$B,"<="&$B4)>0,"NA",AVERAGEIFS(monthly!N:N,monthly!$A:$A,">="&$A4,monthly!$B:$B,"<="&$B4)) -> NA | W4: =IF(COUNTIFS(monthly!O:O,"",monthly!$A:$A,">="&$A4,monthly!$B:$B,"<="&$B4)>0,"NA",AVERAGEIFS(monthly!O:O,monthly!$A:$A,">="&$A4,monthly!$B:$B,"<="&$B4)) -> NA | X4: =IF(COUNTIFS(monthly!P:P,"",monthly!$A:$A,">="&$A4,monthly!$B:$B,"<="&$B4)>0,"NA",AVERAGEIFS(monthly!P:P,monthly!$A:$A,">="&$A4,monthly!$B:$B,"<="&$B4)) -> NA | Y4: =IF(COUNTIFS(monthly!Q:Q,"",monthly!$A:$A,">="&$A4,monthly!$B:$B,"<="&$B4)>0,"NA",AVERAGEIFS(monthly!Q:Q,monthly!$A:$A,">="&$A4,monthly!$B:$B,"<="&$B4)) -> 6.8766667 | Z4: =IF(COUNTIFS(monthly!R:R,"",monthly!$A:$A,">="&$A4,monthly!$B:$B,"<="&$B4)>0,"NA",AVERAGEIFS(monthly!R:R,monthly!$A:$A,">="&$A4,monthly!$B:$B,"<="&$B4)) -> 7.4579798 | AA4: =IF(COUNTIFS(monthly!S:S,"",monthly!$A:$A,">="&$A4,monthly!$B:$B,"<="&$B4)>0,"NA",AVERAGEIFS(monthly!S:S,monthly!$A:$A,">="&$A4,monthly!$B:$B,"<="&$B4)) -> -0.58131313 | AB4: =IF(COUNTIFS(monthly!T:T,"",monthly!$A:$A,">="&$A4,monthly!$B:$B,"<="&$B4)>0,"NA",AVERAGEIFS(monthly!T:T,monthly!$A:$A,">="&$A4,monthly!$B:$B,"<="&$B4)) -> NA | AC4: =IF(COUNTIFS(monthly!U:U,"",monthly!$A:$A,">="&$A4,monthly!$B:$B,"<="&$B4)>0,"NA",AVERAGEIFS(monthly!U:U,monthly!$A:$A,">="&$A4,monthly!$B:$B,"<="&$B4)) -> NA | AD4: =IF(COUNTIFS(monthly!V:V,"",monthly!$A:$A,">="&$A4,monthly!$B:$B,"<="&$B4)>0,"NA",AVERAGEIFS(monthly!V:V,monthly!$A:$A,">="&$A4,monthly!$B:$B,"<="&$B4)) -> NA | AE4: =IF(COUNTIFS(monthly!W:W,"",monthly!$A:$A,">="&$A4,monthly!$B:$B,"<="&$B4)>0,"NA",AVERAGEIFS(monthly!W:W,monthly!$A:$A,">="&$A4,monthly!$B:$B,"<="&$B4)) -> NA | AF4: =IF(COUNTIFS(monthly!X:X,"",monthly!$A:$A,">="&$A4,monthly!$B:$B,"<="&$B4)>0,"NA",AVERAGEIFS(monthly!X:X,monthly!$A:$A,">="&$A4,monthly!$B:$B,"<="&$B4)) -> NA | AG4: =IF(COUNTIFS(monthly!Y:Y,"",monthly!$A:$A,">="&$A4,monthly!$B:$B,"<="&$B4)>0,"NA",AVERAGEIFS(monthly!Y:Y,monthly!$A:$A,">="&$A4,monthly!$B:$B,"<="&$B4)) -> NA | AH4: =IF(COUNTIFS(monthly!Z:Z,"",monthly!$A:$A,">="&$A4,monthly!$B:$B,"<="&$B4)>0,"NA",AVERAGEIFS(monthly!Z:Z,monthly!$A:$A,">="&$A4,monthly!$B:$B,"<="&$B4)) -> NA
A5: 25842 | B5: 25932 | C5: =IF(ISBLANK(VLOOKUP($A5,quarterly_data,MATCH(C$1,quarterly!$1:$1,FALSE),FALSE)),"NA",VLOOKUP($A5,quarterly_data,MATCH(C$1,quarterly!$1:$1,FALSE),FALSE)) -> 145.17265 | D5: =IF(ISBLANK(VLOOKUP($A5,quarterly_data,MATCH(D$1,quarterly!$1:$1,FALSE),FALSE)),"NA",VLOOKUP($A5,quarterly_data,MATCH(D$1,quarterly!$1:$1,FALSE),FALSE)) -> 55.6 | E5: =IF(ISBLANK(VLOOKUP($A5,quarterly_data,MATCH(E$1,quarterly!$1:$1,FALSE),FALSE)),"NA",VLOOKUP($A5,quarterly_data,MATCH(E$1,quarterly!$1:$1,FALSE),FALSE)) -> 0.3646308 | F5: =IF(ISBLANK(VLOOKUP($A5,quarterly_data,MATCH(F$1,quarterly!$1:$1,FALSE),FALSE)),"NA",VLOOKUP($A5,quarterly_data,MATCH(F$1,quarterly!$1:$1,FALSE),FALSE)) -> 0.0802361 | G5: =IF(ISBLANK(VLOOKUP($A5,quarterly_data,MATCH(G$1,quarterly!$1:$1,FALSE),FALSE)),"NA",VLOOKUP($A5,quarterly_data,MATCH(G$1,quarterly!$1:$1,FALSE),FALSE)) -> 5299.672 | H5: =IF(ISBLANK(VLOOKUP($A5,quarterly_data,MATCH(H$1,quarterly!$1:$1,FALSE),FALSE)),"NA",VLOOKUP($A5,quarterly_data,MATCH(H$1,quarterly!$1:$1,FALSE),FALSE)) -> 139332 | I5: =IF(ISBLANK(VLOOKUP($A5,quarterly_data,MATCH(I$1,quarterly!$1:$1,FALSE),FALSE)),"NA",VLOOKUP($A5,quarterly_data,MATCH(I$1,quarterly!$1:$1,FALSE),FALSE)) -> NA | J5: =IF(ISBLANK(VLOOKUP($A5,quarterly_data,MATCH(J$1,quarterly!$1:$1,FALSE),FALSE)),"NA",VLOOKUP($A5,quarterly_data,MATCH(J$1,quarterly!$1:$1,FALSE),FALSE)) -> 6.92 | K5: =IF(COUNTIFS(monthly!C:C,"",monthly!$A:$A,">="&$A5,monthly!$B:$B,"<="&$B5)>0,"NA",AVERAGEIFS(monthly!C:C,monthly!$A:$A,">="&$A5,monthly!$B:$B,"<="&$B5)) -> 99.2 | L5: =IF(COUNTIFS(monthly!D:D,"",monthly!$A:$A,">="&$A5,monthly!$B:$B,"<="&$B5)>0,"NA",AVERAGEIFS(monthly!D:D,monthly!$A:$A,">="&$A5,monthly!$B:$B,"<="&$B5)) -> 1.1131 | M5: =IF(COUNTIFS(monthly!E:E,"",monthly!$A:$A,">="&$A5,monthly!$B:$B,"<="&$B5)>0,"NA",AVERAGEIFS(monthly!E:E,monthly!$A:$A,">="&$A5,monthly!$B:$B,"<="&$B5)) -> NA | N5: =IF(COUNTIFS(monthly!F:F,"",monthly!$A:$A,">="&$A5,monthly!$B:$B,"<="&$B5)>0,"NA",AVERAGEIFS(monthly!F:F,monthly!$A:$A,">="&$A5,monthly!$B:$B,"<="&$B5)) -> NA | O5: =IF(COUNTIFS(monthly!G:G,"",monthly!$A:$A,">="&$A5,monthly!$B:$B,"<="&$B5)>0,"NA",AVERAGEIFS(monthly!G:G,monthly!$A:$A,">="&$A5,monthly!$B:$B,"<="&$B5)) -> 9.8 | P5: =IF(COUNTIFS(monthly!H:H,"",monthly!$A:$A,">="&$A5,monthly!$B:$B,"<="&$B5)>0,"NA",AVERAGEIFS(monthly!H:H,monthly!$A:$A,">="&$A5,monthly!$B:$B,"<="&$B5)) -> 7.8 | Q5: =IF(COUNTIFS(monthly!I:I,"",monthly!$A:$A,">="&$A5,monthly!$B:$B,"<="&$B5)>0,"NA",AVERAGEIFS(monthly!I:I,monthly!$A:$A,">="&$A5,monthly!$B:$B,"<="&$B5)) -> 1.2 | R5: =IF(COUNTIFS(monthly!J:J,"",monthly!$A:$A,">="&$A5,monthly!$B:$B,"<="&$B5)>0,"NA",AVERAGEIFS(monthly!J:J,monthly!$A:$A,">="&$A5,monthly!$B:$B,"<="&$B5)) -> NA | S5: =IF(COUNTIFS(monthly!K:K,"",monthly!$A:$A,">="&$A5,monthly!$B:$B,"<="&$B5)>0,"NA",AVERAGEIFS(monthly!K:K,monthly!$A:$A,">="&$A5,monthly!$B:$B,"<="&$B5)) -> NA | T5: =IF(COUNTIFS(monthly!L:L,"",monthly!$A:$A,">="&$A5,monthly!$B:$B,"<="&$B5)>0,"NA",AVERAGEIFS(monthly!L:L,monthly!$A:$A,">="&$A5,monthly!$B:$B,"<="&$B5)) -> 5.9026022 | U5: =IF(COUNTIFS(monthly!M:M,"",monthly!$A:$A,">="&$A5,monthly!$B:$B,"<="&$B5)>0,"NA",AVERAGEIFS(monthly!M:M,monthly!$A:$A,">="&$A5,monthly!$B:$B,"<="&$B5)) -> NA | V5: =IF(COUNTIFS(monthly!N:N,"",monthly!$A:$A,">="&$A5,monthly!$B:$B,"<="&$B5)>0,"NA",AVERAGEIFS(monthly!N:N,monthly!$A:$A,">="&$A5,monthly!$B:$B,"<="&$B5)) -> NA | W5: =IF(COUNTIFS(monthly!O:O,"",monthly!$A:$A,">="&$A5,monthly!$B:$B,"<="&$B5)>0,"NA",AVERAGEIFS(monthly!O:O,monthly!$A:$A,">="&$A5,monthly!$B:$B,"<="&$B5)) -> NA | X5: =IF(COUNTIFS(monthly!P:P,"",monthly!$A:$A,">="&$A5,monthly!$B:$B,"<="&$B5)>0,"NA",AVERAGEIFS(monthly!P:P,monthly!$A:$A,">="&$A5,monthly!$B:$B,"<="&$B5)) -> NA | Y5: =IF(COUNTIFS(monthly!Q:Q,"",monthly!$A:$A,">="&$A5,monthly!$B:$B,"<="&$B5)>0,"NA",AVERAGEIFS(monthly!Q:Q,monthly!$A:$A,">="&$A5,monthly!$B:$B,"<="&$B5)) -> 6.855 | Z5: =IF(COUNTIFS(monthly!R:R,"",monthly!$A:$A,">="&$A5,monthly!$B:$B,"<="&$B5)>0,"NA",AVERAGEIFS(monthly!R:R,monthly!$A:$A,">="&$A5,monthly!$B:$B,"<="&$B5)) -> 7.0838889 | AA5: =IF(COUNTIFS(monthly!S:S,"",monthly!$A:$A,">="&$A5,monthly!$B:$B,"<="&$B5)>0,"NA",AVERAGEIFS(monthly!S:S,monthly!$A:$A,">="&$A5,monthly!$B:$B,"<="&$B5)) -> -0.22888889 | AB5: =IF(COUNTIFS(monthly!T:T,"",monthly!$A:$A,">="&$A5,monthly!$B:$B,"<="&$B5)>0,"NA",AVERAGEIFS(monthly!T:T,monthly!$A:$A,">="&$A5,monthly!$B:$B,"<="&$B5)) -> NA | AC5: =IF(COUNTIFS(monthly!U:U,"",monthly!$A:$A,">="&$A5,monthly!$B:$B,"<="&$B5)>0,"NA",AVERAGEIFS(monthly!U:U,monthly!$A:$A,">="&$A5,monthly!$B:$B,"<="&$B5)) -> NA | AD5: =IF(COUNTIFS(monthly!V:V,"",monthly!$A:$A,">="&$A5,monthly!$B:$B,"<="&$B5)>0,"NA",AVERAGEIFS(monthly!V:V,monthly!$A:$A,">="&$A5,monthly!$B:$B,"<="&$B5)) -> NA | AE5: =IF(COUNTIFS(monthly!W:W,"",monthly!$A:$A,">="&$A5,monthly!$B:$B,"<="&$B5)>0,"NA",AVERAGEIFS(monthly!W:W,monthly!$A:$A,">="&$A5,monthly!$B:$B,"<="&$B5)) -> NA | AF5: =IF(COUNTIFS(monthly!X:X,"",monthly!$A:$A,">="&$A5,monthly!$B:$B,"<="&$B5)>0,"NA",AVERAGEIFS(monthly!X:X,monthly!$A:$A,">="&$A5,monthly!$B:$B,"<="&$B5)) -> NA | AG5: =IF(COUNTIFS(monthly!Y:Y,"",monthly!$A:$A,">="&$A5,monthly!$B:$B,"<="&$B5)>0,"NA",AVERAGEIFS(monthly!Y:Y,monthly!$A:$A,">="&$A5,monthly!$B:$B,"<="&$B5)) -> NA | AH5: =IF(COUNTIFS(monthly!Z:Z,"",monthly!$A:$A,">="&$A5,monthly!$B:$B,"<="&$B5)>0,"NA",AVERAGEIFS(monthly!Z:Z,monthly!$A:$A,">="&$A5,monthly!$B:$B,"<="&$B5)) -> NA
A6: 25934 | B6: 26022 | C6: =IF(ISBLANK(VLOOKUP($A6,quarterly_data,MATCH(C$1,quarterly!$1:$1,FALSE),FALSE)),"NA",VLOOKUP($A6,quarterly_data,MATCH(C$1,quarterly!$1:$1,FALSE),FALSE)) -> 146.01779 | D6: =IF(ISBLANK(VLOOKUP($A6,quarterly_data,MATCH(D$1,quarterly!$1:$1,FALSE),FALSE)),"NA",VLOOKUP($A6,quarterly_data,MATCH(D$1,quarterly!$1:$1,FALSE),FALSE)) -> 55.9 | E6: =IF(ISBLANK(VLOOKUP($A6,quarterly_data,MATCH(E$1,quarterly!$1:$1,FALSE),FALSE)),"NA",VLOOKUP($A6,quarterly_data,MATCH(E$1,quarterly!$1:$1,FALSE),FALSE)) -> 0.655308 | F6: =IF(ISBLANK(VLOOKUP($A6,quarterly_data,MATCH(F$1,quarterly!$1:$1,FALSE),FALSE)),"NA",VLOOKUP($A6,quarterly_data,MATCH(F$1,quarterly!$1:$1,FALSE),FALSE)) -> 0.1675247 | G6: =IF(ISBLANK(VLOOKUP($A6,quarterly_data,MATCH(G$1,quarterly!$1:$1,FALSE),FALSE)),"NA",VLOOKUP($A6,quarterly_data,MATCH(G$1,quarterly!$1:$1,FALSE),FALSE)) -> 5443.619 | H6: =IF(ISBLANK(VLOOKUP($A6,quarterly_data,MATCH(H$1,quarterly!$1:$1,FALSE),FALSE)),"NA",VLOOKUP($A6,quarterly_data,MATCH(H$1,quarterly!$1:$1,FALSE),FALSE)) -> 141071 | I6: =IF(ISBLANK(VLOOKUP($A6,quarterly_data,MATCH(I$1,quarterly!$1:$1,FALSE),FALSE)),"NA",VLOOKUP($A6,quarterly_data,MATCH(I$1,quarterly!$1:$1,FALSE),FALSE)) -> NA | J6: =IF(ISBLANK(VLOOKUP($A6,quarterly_data,MATCH(J$1,quarterly!$1:$1,FALSE),FALSE)),"NA",VLOOKUP($A6,quarterly_data,MATCH(J$1,quarterly!$1:$1,FALSE),FALSE)) -> 7 | K6: =IF(COUNTIFS(monthly!C:C,"",monthly!$A:$A,">="&$A6,monthly!$B:$B,"<="&$B6)>0,"NA",AVERAGEIFS(monthly!C:C,monthly!$A:$A,">="&$A6,monthly!$B:$B,"<="&$B6)) -> 100 | L6: =IF(COUNTIFS(monthly!D:D,"",monthly!$A:$A,">="&$A6,monthly!$B:$B,"<="&$B6)>0,"NA",AVERAGEIFS(monthly!D:D,monthly!$A:$A,">="&$A6,monthly!$B:$B,"<="&$B6)) -> 1.12595 | M6: =IF(COUNTIFS(monthly!E:E,"",monthly!$A:$A,">="&$A6,monthly!$B:$B,"<="&$B6)>0,"NA",AVERAGEIFS(monthly!E:E,monthly!$A:$A,">="&$A6,monthly!$B:$B,"<="&$B6)) -> NA | N6: =IF(COUNTIFS(monthly!F:F,"",monthly!$A:$A,">="&$A6,monthly!$B:$B,"<="&$B6)>0,"NA",AVERAGEIFS(monthly!F:F,monthly!$A:$A,">="&$A6,monthly!$B:$B,"<="&$B6)) -> NA | O6: =IF(COUNTIFS(monthly!G:G,"",monthly!$A:$A,">="&$A6,monthly!$B:$B,"<="&$B6)>0,"NA",AVERAGEIFS(monthly!G:G,monthly!$A:$A,">="&$A6,monthly!$B:$B,"<="&$B6)) -> 10.3 | P6: =IF(COUNTIFS(monthly!H:H,"",monthly!$A:$A,">="&$A6,monthly!$B:$B,"<="&$B6)>0,"NA",AVERAGEIFS(monthly!H:H,monthly!$A:$A,">="&$A6,monthly!$B:$B,"<="&$B6)) -> 8.7 | Q6: =IF(COUNTIFS(monthly!I:I,"",monthly!$A:$A,">="&$A6,monthly!$B:$B,"<="&$B6)>0,"NA",AVERAGEIFS(monthly!I:I,monthly!$A:$A,">="&$A6,monthly!$B:$B,"<="&$B6)) -> 1.6 | R6: =IF(COUNTIFS(monthly!J:J,"",monthly!$A:$A,">="&$A6,monthly!$B:$B,"<="&$B6)>0,"NA",AVERAGEIFS(monthly!J:J,monthly!$A:$A,">="&$A6,monthly!$B:$B,"<="&$B6)) -> NA | S6: =IF(COUNTIFS(monthly!K:K,"",monthly!$A:$A,">="&$A6,monthly!$B:$B,"<="&$B6)>0,"NA",AVERAGEIFS(monthly!K:K,monthly!$A:$A,">="&$A6,monthly!$B:$B,"<="&$B6)) -> NA | T6: =IF(COUNTIFS(monthly!L:L,"",monthly!$A:$A,">="&$A6,monthly!$B:$B,"<="&$B6)>0,"NA",AVERAGEIFS(monthly!L:L,monthly!$A:$A,">="&$A6,monthly!$B:$B,"<="&$B6)) -> 3.9314862 | U6: =IF(COUNTIFS(monthly!M:M,"",monthly!$A:$A,">="&$A6,monthly!$B:$B,"<="&$B6)>0,"NA",AVERAGEIFS(monthly!M:M,monthly!$A:$A,">="&$A6,monthly!$B:$B,"<="&$B6)) -> NA | V6: =IF(COUNTIFS(monthly!N:N,"",monthly!$A:$A,">="&$A6,monthly!$B:$B,"<="&$B6)>0,"NA",AVERAGEIFS(monthly!N:N,monthly!$A:$A,">="&$A6,monthly!$B:$B,"<="&$B6)) -> NA | W6: =IF(COUNTIFS(monthly!O:O,"",monthly!$A:$A,">="&$A6,monthly!$B:$B,"<="&$B6)>0,"NA",AVERAGEIFS(monthly!O:O,monthly!$A:$A,">="&$A6,monthly!$B:$B,"<="&$B6)) -> NA | X6: =IF(COUNTIFS(monthly!P:P,"",monthly!$A:$A,">="&$A6,monthly!$B:$B,"<="&$B6)>0,"NA",AVERAGEIFS(monthly!P:P,monthly!$A:$A,">="&$A6,monthly!$B:$B,"<="&$B6)) -> NA | Y6: =IF(COUNTIFS(monthly!Q:Q,"",monthly!$A:$A,">="&$A6,monthly!$B:$B,"<="&$B6)>0,"NA",AVERAGEIFS(monthly!Q:Q,monthly!$A:$A,">="&$A6,monthly!$B:$B,"<="&$B6)) -> 6.85 | Z6: =IF(COUNTIFS(monthly!R:R,"",monthly!$A:$A,">="&$A6,monthly!$B:$B,"<="&$B6)>0,"NA",AVERAGEIFS(monthly!R:R,monthly!$A:$A,">="&$A6,monthly!$B:$B,"<="&$B6)) -> 6.1753611 | AA6: =IF(COUNTIFS(monthly!S:S,"",monthly!$A:$A,">="&$A6,monthly!$B:$B,"<="&$B6)>0,"NA",AVERAGEIFS(monthly!S:S,monthly!$A:$A,">="&$A6,monthly!$B:$B,"<="&$B6)) -> 0.67463889 | AB6: =IF(COUNTIFS(monthly!T:T,"",monthly!$A:$A,">="&$A6,monthly!$B:$B,"<="&$B6)>0,"NA",AVERAGEIFS(monthly!T:T,monthly!$A:$A,">="&$A6,monthly!$B:$B,"<="&$B6)) -> NA | AC6: =IF(COUNTIFS(monthly!U:U,"",monthly!$A:$A,">="&$A6,monthly!$B:$B,"<="&$B6)>0,"NA",AVERAGEIFS(monthly!U:U,monthly!$A:$A,">="&$A6,monthly!$B:$B,"<="&$B6)) -> NA | AD6: =IF(COUNTIFS(monthly!V:V,"",monthly!$A:$A,">="&$A6,monthly!$B:$B,"<="&$B6)>0,"NA",AVERAGEIFS(monthly!V:V,monthly!$A:$A,">="&$A6,monthly!$B:$B,"<="&$B6)) -> NA | AE6: =IF(COUNTIFS(monthly!W:W,"",monthly!$A:$A,">="&$A6,monthly!$B:$B,"<="&$B6)>0,"NA",AVERAGEIFS(monthly!W:W,monthly!$A:$A,">="&$A6,monthly!$B:$B,"<="&$B6)) -> NA | AF6: =IF(COUNTIFS(monthly!X:X,"",monthly!$A:$A,">="&$A6,monthly!$B:$B,"<="&$B6)>0,"NA",AVERAGEIFS(monthly!X:X,monthly!$A:$A,">="&$A6,monthly!$B:$B,"<="&$B6)) -> NA | AG6: =IF(COUNTIFS(monthly!Y:Y,"",monthly!$A:$A,">="&$A6,monthly!$B:$B,"<="&$B6)>0,"NA",AVERAGEIFS(monthly!Y:Y,monthly!$A:$A,">="&$A6,monthly!$B:$B,"<="&$B6)) -> NA | AH6: =IF(COUNTIFS(monthly!Z:Z,"",monthly!$A:$A,">="&$A6,monthly!$B:$B,"<="&$B6)>0,"NA",AVERAGEIFS(monthly!Z:Z,monthly!$A:$A,">="&$A6,monthly!$B:$B,"<="&$B6)) -> NA
A7: 26024 | B7: 26114 | C7: =IF(ISBLANK(VLOOKUP($A7,quarterly_data,MATCH(C$1,quarterly!$1:$1,FALSE),FALSE)),"NA",VLOOKUP($A7,quarterly_data,MATCH(C$1,quarterly!$1:$1,FALSE),FALSE)) -> 147.05388 | D7: =IF(ISBLANK(VLOOKUP($A7,quarterly_data,MATCH(D$1,quarterly!$1:$1,FALSE),FALSE)),"NA",VLOOKUP($A7,quarterly_data,MATCH(D$1,quarterly!$1:$1,FALSE),FALSE)) -> 54.7 | E7: =IF(ISBLANK(VLOOKUP($A7,quarterly_data,MATCH(E$1,quarterly!$1:$1,FALSE),FALSE)),"NA",VLOOKUP($A7,quarterly_data,MATCH(E$1,quarterly!$1:$1,FALSE),FALSE)) -> 0 | F7: =IF(ISBLANK(VLOOKUP($A7,quarterly_data,MATCH(F$1,quarterly!$1:$1,FALSE),FALSE)),"NA",VLOOKUP($A7,quarterly_data,MATCH(F$1,quarterly!$1:$1,FALSE),FALSE)) -> 0.0776852 | G7: =IF(ISBLANK(VLOOKUP($A7,quarterly_data,MATCH(G$1,quarterly!$1:$1,FALSE),FALSE)),"NA",VLOOKUP($A7,quarterly_data,MATCH(G$1,quarterly!$1:$1,FALSE),FALSE)) -> 5473.059 | H7: =IF(ISBLANK(VLOOKUP($A7,quarterly_data,MATCH(H$1,quarterly!$1:$1,FALSE),FALSE)),"NA",VLOOKUP($A7,quarterly_data,MATCH(H$1,quarterly!$1:$1,FALSE),FALSE)) -> 141684 | I7: =IF(ISBLANK(VLOOKUP($A7,quarterly_data,MATCH(I$1,quarterly!$1:$1,FALSE),FALSE)),"NA",VLOOKUP($A7,quarterly_data,MATCH(I$1,quarterly!$1:$1,FALSE),FALSE)) -> NA | J7: =IF(ISBLANK(VLOOKUP($A7,quarterly_data,MATCH(J$1,quarterly!$1:$1,FALSE),FALSE)),"NA",VLOOKUP($A7,quarterly_data,MATCH(J$1,quarterly!$1:$1,FALSE),FALSE)) -> 7.11 | K7: =IF(COUNTIFS(monthly!C:C,"",monthly!$A:$A,">="&$A7,monthly!$B:$B,"<="&$B7)>0,"NA",AVERAGEIFS(monthly!C:C,monthly!$A:$A,">="&$A7,monthly!$B:$B,"<="&$B7)) -> 99.866667 | L7: =IF(COUNTIFS(monthly!D:D,"",monthly!$A:$A,">="&$A7,monthly!$B:$B,"<="&$B7)>0,"NA",AVERAGEIFS(monthly!D:D,monthly!$A:$A,">="&$A7,monthly!$B:$B,"<="&$B7)) -> 1.1264667 | M7: =IF(COUNTIFS(monthly!E:E,"",monthly!$A:$A,">="&$A7,monthly!$B:$B,"<="&$B7)>0,"NA",AVERAGEIFS(monthly!E:E,monthly!$A:$A,">="&$A7,monthly!$B:$B,"<="&$B7)) -> NA | N7: =IF(COUNTIFS(monthly!F:F,"",monthly!$A:$A,">="&$A7,monthly!$B:$B,"<="&$B7)>0,"NA",AVERAGEIFS(monthly!F:F,monthly!$A:$A,">="&$A7,monthly!$B:$B,"<="&$B7)) -> NA | O7: =IF(COUNTIFS(monthly!G:G,"",monthly!$A:$A,">="&$A7,monthly!$B:$B,"<="&$B7)>0,"NA",AVERAGEIFS(monthly!G:G,monthly!$A:$A,">="&$A7,monthly!$B:$B,"<="&$B7)) -> 10.3 | P7: =IF(COUNTIFS(monthly!H:H,"",monthly!$A:$A,">="&$A7,monthly!$B:$B,"<="&$B7)>0,"NA",AVERAGEIFS(monthly!H:H,monthly!$A:$A,">="&$A7,monthly!$B:$B,"<="&$B7)) -> 8.7 | Q7: =IF(COUNTIFS(monthly!I:I,"",monthly!$A:$A,">="&$A7,monthly!$B:$B,"<="&$B7)>0,"NA",AVERAGEIFS(monthly!I:I,monthly!$A:$A,">="&$A7,monthly!$B:$B,"<="&$B7)) -> 1.6 | R7: =IF(COUNTIFS(monthly!J:J,"",monthly!$A:$A,">="&$A7,monthly!$B:$B,"<="&$B7)>0,"NA",AVERAGEIFS(monthly!J:J,monthly!$A:$A,">="&$A7,monthly!$B:$B,"<="&$B7)) -> NA | S7: =IF(COUNTIFS(monthly!K:K,"",monthly!$A:$A,">="&$A7,monthly!$B:$B,"<="&$B7)>0,"NA",AVERAGEIFS(monthly!K:K,monthly!$A:$A,">="&$A7,monthly!$B:$B,"<="&$B7)) -> NA | T7: =IF(COUNTIFS(monthly!L:L,"",monthly!$A:$A,">="&$A7,monthly!$B:$B,"<="&$B7)>0,"NA",AVERAGEIFS(monthly!L:L,monthly!$A:$A,">="&$A7,monthly!$B:$B,"<="&$B7)) -> 4.5665305 | U7: =IF(COUNTIFS(monthly!M:M,"",monthly!$A:$A,">="&$A7,monthly!$B:$B,"<="&$B7)>0,"NA",AVERAGEIFS(monthly!M:M,monthly!$A:$A,">="&$A7,monthly!$B:$B,"<="&$B7)) -> NA | V7: =IF(COUNTIFS(monthly!N:N,"",monthly!$A:$A,">="&$A7,monthly!$B:$B,"<="&$B7)>0,"NA",AVERAGEIFS(monthly!N:N,monthly!$A:$A,">="&$A7,monthly!$B:$B,"<="&$B7)) -> NA | W7: =IF(COUNTIFS(monthly!O:O,"",monthly!$A:$A,">="&$A7,monthly!$B:$B,"<="&$B7)>0,"NA",AVERAGEIFS(monthly!O:O,monthly!$A:$A,">="&$A7,monthly!$B:$B,"<="&$B7)) -> NA | X7: =IF(COUNTIFS(monthly!P:P,"",monthly!$A:$A,">="&$A7,monthly!$B:$B,"<="&$B7)>0,"NA",AVERAGEIFS(monthly!P:P,monthly!$A:$A,">="&$A7,monthly!$B:$B,"<="&$B7)) -> NA | Y7: =IF(COUNTIFS(monthly!Q:Q,"",monthly!$A:$A,">="&$A7,monthly!$B:$B,"<="&$B7)>0,"NA",AVERAGEIFS(monthly!Q:Q,monthly!$A:$A,">="&$A7,monthly!$B:$B,"<="&$B7)) -> 6.8333333 | Z7: =IF(COUNTIFS(monthly!R:R,"",monthly!$A:$A,">="&$A7,monthly!$B:$B,"<="&$B7)>0,"NA",AVERAGEIFS(monthly!R:R,monthly!$A:$A,">="&$A7,monthly!$B:$B,"<="&$B7)) -> 6.2495274 | AA7: =IF(COUNTIFS(monthly!S:S,"",monthly!$A:$A,">="&$A7,monthly!$B:$B,"<="&$B7)>0,"NA",AVERAGEIFS(monthly!S:S,monthly!$A:$A,">="&$A7,monthly!$B:$B,"<="&$B7)) -> 0.58380592 | AB7: =IF(COUNTIFS(monthly!T:T,"",monthly!$A:$A,">="&$A7,monthly!$B:$B,"<="&$B7)>0,"NA",AVERAGEIFS(monthly!T:T,monthly!$A:$A,">="&$A7,monthly!$B:$B,"<="&$B7)) -> NA | AC7: =IF(COUNTIFS(monthly!U:U,"",monthly!$A:$A,">="&$A7,monthly!$B:$B,"<="&$B7)>0,"NA",AVERAGEIFS(monthly!U:U,monthly!$A:$A,">="&$A7,monthly!$B:$B,"<="&$B7)) -> NA | AD7: =IF(COUNTIFS(monthly!V:V,"",monthly!$A:$A,">="&$A7,monthly!$B:$B,"<="&$B7)>0,"NA",AVERAGEIFS(monthly!V:V,monthly!$A:$A,">="&$A7,monthly!$B:$B,"<="&$B7)) -> NA | AE7: =IF(COUNTIFS(monthly!W:W,"",monthly!$A:$A,">="&$A7,monthly!$B:$B,"<="&$B7)>0,"NA",AVERAGEIFS(monthly!W:W,monthly!$A:$A,">="&$A7,monthly!$B:$B,"<="&$B7)) -> NA | AF7: =IF(COUNTIFS(monthly!X:X,"",monthly!$A:$A,">="&$A7,monthly!$B:$B,"<="&$B7)>0,"NA",AVERAGEIFS(monthly!X:X,monthly!$A:$A,">="&$A7,monthly!$B:$B,"<="&$B7)) -> NA | AG7: =IF(COUNTIFS(monthly!Y:Y,"",monthly!$A:$A,">="&$A7,monthly!$B:$B,"<="&$B7)>0,"NA",AVERAGEIFS(monthly!Y:Y,monthly!$A:$A,">="&$A7,monthly!$B:$B,"<="&$B7)) -> NA | AH7: =IF(COUNTIFS(monthly!Z:Z,"",monthly!$A:$A,">="&$A7,monthly!$B:$B,"<="&$B7)>0,"NA",AVERAGEIFS(monthly!Z:Z,monthly!$A:$A,">="&$A7,monthly!$B:$B,"<="&$B7)) -> NA
A8: 26115 | B8: 26206 | C8: =IF(ISBLANK(VLOOKUP($A8,quarterly_data,MATCH(C$1,quarterly!$1:$1,FALSE),FALSE)),"NA",VLOOKUP($A8,quarterly_data,MATCH(C$1,quarterly!$1:$1,FALSE),FALSE)) -> 146.56491 | D8: =IF(ISBLANK(VLOOKUP($A8,quarterly_data,MATCH(D$1,quarterly!$1:$1,FALSE),FALSE)),"NA",VLOOKUP($A8,quarterly_data,MATCH(D$1,quarterly!$1:$1,FALSE),FALSE)) -> 55.5 | E8: =IF(ISBLANK(VLOOKUP($A8,quarterly_data,MATCH(E$1,quarterly!$1:$1,FALSE),FALSE)),"NA",VLOOKUP($A8,quarterly_data,MATCH(E$1,quarterly!$1:$1,FALSE),FALSE)) -> 0.337344 | F8: =IF(ISBLANK(VLOOKUP($A8,quarterly_data,MATCH(F$1,quarterly!$1:$1,FALSE),FALSE)),"NA",VLOOKUP($A8,quarterly_data,MATCH(F$1,quarterly!$1:$1,FALSE),FALSE)) -> 0.0893124 | G8: =IF(ISBLANK(VLOOKUP($A8,quarterly_data,MATCH(G$1,quarterly!$1:$1,FALSE),FALSE)),"NA",VLOOKUP($A8,quarterly_data,MATCH(G$1,quarterly!$1:$1,FALSE),FALSE)) -> 5518.072 | H8: =IF(ISBLANK(VLOOKUP($A8,quarterly_data,MATCH(H$1,quarterly!$1:$1,FALSE),FALSE)),"NA",VLOOKUP($A8,quarterly_data,MATCH(H$1,quarterly!$1:$1,FALSE),FALSE)) -> 146097 | I8: =IF(ISBLANK(VLOOKUP($A8,quarterly_data,MATCH(I$1,quarterly!$1:$1,FALSE),FALSE)),"NA",VLOOKUP($A8,quarterly_data,MATCH(I$1,quarterly!$1:$1,FALSE),FALSE)) -> NA | J8: =IF(ISBLANK(VLOOKUP($A8,quarterly_data,MATCH(J$1,quarterly!$1:$1,FALSE),FALSE)),"NA",VLOOKUP($A8,quarterly_data,MATCH(J$1,quarterly!$1:$1,FALSE),FALSE)) -> 7.27 | K8: =IF(COUNTIFS(monthly!C:C,"",monthly!$A:$A,">="&$A8,monthly!$B:$B,"<="&$B8)>0,"NA",AVERAGEIFS(monthly!C:C,monthly!$A:$A,">="&$A8,monthly!$B:$B,"<="&$B8)) -> 99.6 | L8: =IF(COUNTIFS(monthly!D:D,"",monthly!$A:$A,">="&$A8,monthly!$B:$B,"<="&$B8)>0,"NA",AVERAGEIFS(monthly!D:D,monthly!$A:$A,">="&$A8,monthly!$B:$B,"<="&$B8)) -> 1.1440333 | M8: =IF(COUNTIFS(monthly!E:E,"",monthly!$A:$A,">="&$A8,monthly!$B:$B,"<="&$B8)>0,"NA",AVERAGEIFS(monthly!E:E,monthly!$A:$A,">="&$A8,monthly!$B:$B,"<="&$B8)) -> NA | N8: =IF(COUNTIFS(monthly!F:F,"",monthly!$A:$A,">="&$A8,monthly!$B:$B,"<="&$B8)>0,"NA",AVERAGEIFS(monthly!F:F,monthly!$A:$A,">="&$A8,monthly!$B:$B,"<="&$B8)) -> NA | O8: =IF(COUNTIFS(monthly!G:G,"",monthly!$A:$A,">="&$A8,monthly!$B:$B,"<="&$B8)>0,"NA",AVERAGEIFS(monthly!G:G,monthly!$A:$A,">="&$A8,monthly!$B:$B,"<="&$B8)) -> 10.3 | P8: =IF(COUNTIFS(monthly!H:H,"",monthly!$A:$A,">="&$A8,monthly!$B:$B,"<="&$B8)>0,"NA",AVERAGEIFS(monthly!H:H,monthly!$A:$A,">="&$A8,monthly!$B:$B,"<="&$B8)) -> 8.7 | Q8: =IF(COUNTIFS(monthly!I:I,"",monthly!$A:$A,">="&$A8,monthly!$B:$B,"<="&$B8)>0,"NA",AVERAGEIFS(monthly!I:I,monthly!$A:$A,">="&$A8,monthly!$B:$B,"<="&$B8)) -> 1.7 | R8: =IF(COUNTIFS(monthly!J:J,"",monthly!$A:$A,">="&$A8,monthly!$B:$B,"<="&$B8)>0,"NA",AVERAGEIFS(monthly!J:J,monthly!$A:$A,">="&$A8,monthly!$B:$B,"<="&$B8)) -> NA | S8: =IF(COUNTIFS(monthly!K:K,"",monthly!$A:$A,">="&$A8,monthly!$B:$B,"<="&$B8)>0,"NA",AVERAGEIFS(monthly!K:K,monthly!$A:$A,">="&$A8,monthly!$B:$B,"<="&$B8)) -> NA | T8: =IF(COUNTIFS(monthly!L:L,"",monthly!$A:$A,">="&$A8,monthly!$B:$B,"<="&$B8)>0,"NA",AVERAGEIFS(monthly!L:L,monthly!$A:$A,">="&$A8,monthly!$B:$B,"<="&$B8)) -> 5.4763835 | U8: =IF(COUNTIFS(monthly!M:M,"",monthly!$A:$A,">="&$A8,monthly!$B:$B,"<="&$B8)>0,"NA",AVERAGEIFS(monthly!M:M,monthly!$A:$A,">="&$A8,monthly!$B:$B,"<="&$B8)) -> NA | V8: =IF(COUNTIFS(monthly!N:N,"",monthly!$A:$A,">="&$A8,monthly!$B:$B,"<="&$B8)>0,"NA",AVERAGEIFS(monthly!N:N,monthly!$A:$A,">="&$A8,monthly!$B:$B,"<="&$B8)) -> NA | W8: =IF(COUNTIFS(monthly!O:O,"",monthly!$A:$A,">="&$A8,monthly!$B:$B,"<="&$B8)>0,"NA",AVERAGEIFS(monthly!O:O,monthly!$A:$A,">="&$A8,monthly!$B:$B,"<="&$B8)) -> NA | X8: =IF(COUNTIFS(monthly!P:P,"",monthly!$A:$A,">="&$A8,monthly!$B:$B,"<="&$B8)>0,"NA",AVERAGEIFS(monthly!P:P,monthly!$A:$A,">="&$A8,monthly!$B:$B,"<="&$B8)) -> NA | Y8: =IF(COUNTIFS(monthly!Q:Q,"",monthly!$A:$A,">="&$A8,monthly!$B:$B,"<="&$B8)>0,"NA",AVERAGEIFS(monthly!Q:Q,monthly!$A:$A,">="&$A8,monthly!$B:$B,"<="&$B8)) -> 6.8033333 | Z8: =IF(COUNTIFS(monthly!R:R,"",monthly!$A:$A,">="&$A8,monthly!$B:$B,"<="&$B8)>0,"NA",AVERAGEIFS(monthly!R:R,monthly!$A:$A,">="&$A8,monthly!$B:$B,"<="&$B8)) -> 6.483925 | AA8: =IF(COUNTIFS(monthly!S:S,"",monthly!$A:$A,">="&$A8,monthly!$B:$B,"<="&$B8)>0,"NA",AVERAGEIFS(monthly!S:S,monthly!$A:$A,">="&$A8,monthly!$B:$B,"<="&$B8)) -> 0.31940837 | AB8: =IF(COUNTIFS(monthly!T:T,"",monthly!$A:$A,">="&$A8,monthly!$B:$B,"<="&$B8)>0,"NA",AVERAGEIFS(monthly!T:T,monthly!$A:$A,">="&$A8,monthly!$B:$B,"<="&$B8)) -> NA | AC8: =IF(COUNTIFS(monthly!U:U,"",monthly!$A:$A,">="&$A8,monthly!$B:$B,"<="&$B8)>0,"NA",AVERAGEIFS(monthly!U:U,monthly!$A:$A,">="&$A8,monthly!$B:$B,"<="&$B8)) -> NA | AD8: =IF(COUNTIFS(monthly!V:V,"",monthly!$A:$A,">="&$A8,monthly!$B:$B,"<="&$B8)>0,"NA",AVERAGEIFS(monthly!V:V,monthly!$A:$A,">="&$A8,monthly!$B:$B,"<="&$B8)) -> NA | AE8: =IF(COUNTIFS(monthly!W:W,"",monthly!$A:$A,">="&$A8,monthly!$B:$B,"<="&$B8)>0,"NA",AVERAGEIFS(monthly!W:W,monthly!$A:$A,">="&$A8,monthly!$B:$B,"<="&$B8)) -> NA | AF8: =IF(COUNTIFS(monthly!X:X,"",monthly!$A:$A,">="&$A8,monthly!$B:$B,"<="&$B8)>0,"NA",AVERAGEIFS(monthly!X:X,monthly!$A:$A,">="&$A8,monthly!$B:$B,"<="&$B8)) -> NA | AG8: =IF(COUNTIFS(monthly!Y:Y,"",monthly!$A:$A,">="&$A8,monthly!$B:$B,"<="&$B8)>0,"NA",AVERAGEIFS(monthly!Y:Y,monthly!$A:$A,">="&$A8,monthly!$B:$B,"<="&$B8)) -> NA | AH8: =IF(COUNTIFS(monthly!Z:Z,"",monthly!$A:$A,">="&$A8,monthly!$B:$B,"<="&$B8)>0,"NA",AVERAGEIFS(monthly!Z:Z,monthly!$A:$A,">="&$A8,monthly!$B:$B,"<="&$B8)) -> NA
A9: 26207 | B9: 26297 | C9: =IF(ISBLANK(VLOOKUP($A9,quarterly_data,MATCH(C$1,quarterly!$1:$1,FALSE),FALSE)),"NA",VLOOKUP($A9,quarterly_data,MATCH(C$1,quarterly!$1:$1,FALSE),FALSE)) -> 147.06334 | D9: =IF(ISBLANK(VLOOKUP($A9,quarterly_data,MATCH(D$1,quarterly!$1:$1,FALSE),FALSE)),"NA",VLOOKUP($A9,quarterly_data,MATCH(D$1,quarterly!$1:$1,FALSE),FALSE)) -> 48.6 | E9: =IF(ISBLANK(VLOOKUP($A9,quarterly_data,MATCH(E$1,quarterly!$1:$1,FALSE),FALSE)),"NA",VLOOKUP($A9,quarterly_data,MATCH(E$1,quarterly!$1:$1,FALSE),FALSE)) -> 0.449169 | F9: =IF(ISBLANK(VLOOKUP($A9,quarterly_data,MATCH(F$1,quarterly!$1:$1,FALSE),FALSE)),"NA",VLOOKUP($A9,quarterly_data,MATCH(F$1,quarterly!$1:$1,FALSE),FALSE)) -> 0.1235682 | G9: =IF(ISBLANK(VLOOKUP($A9,quarterly_data,MATCH(G$1,quarterly!$1:$1,FALSE),FALSE)),"NA",VLOOKUP($A9,quarterly_data,MATCH(G$1,quarterly!$1:$1,FALSE),FALSE)) -> 5531.032 | H9: =IF(ISBLANK(VLOOKUP($A9,quarterly_data,MATCH(H$1,quarterly!$1:$1,FALSE),FALSE)),"NA",VLOOKUP($A9,quarterly_data,MATCH(H$1,quarterly!$1:$1,FALSE),FALSE)) -> 145625 | I9: =IF(ISBLANK(VLOOKUP($A9,quarterly_data,MATCH(I$1,quarterly!$1:$1,FALSE),FALSE)),"NA",VLOOKUP($A9,quarterly_data,MATCH(I$1,quarterly!$1:$1,FALSE),FALSE)) -> NA | J9: =IF(ISBLANK(VLOOKUP($A9,quarterly_data,MATCH(J$1,quarterly!$1:$1,FALSE),FALSE)),"NA",VLOOKUP($A9,quarterly_data,MATCH(J$1,quarterly!$1:$1,FALSE),FALSE)) -> 7.42 | K9: =IF(COUNTIFS(monthly!C:C,"",monthly!$A:$A,">="&$A9,monthly!$B:$B,"<="&$B9)>0,"NA",AVERAGEIFS(monthly!C:C,monthly!$A:$A,">="&$A9,monthly!$B:$B,"<="&$B9)) -> 99.35 | L9: =IF(COUNTIFS(monthly!D:D,"",monthly!$A:$A,">="&$A9,monthly!$B:$B,"<="&$B9)>0,"NA",AVERAGEIFS(monthly!D:D,monthly!$A:$A,">="&$A9,monthly!$B:$B,"<="&$B9)) -> 1.16145 | M9: =IF(COUNTIFS(monthly!E:E,"",monthly!$A:$A,">="&$A9,monthly!$B:$B,"<="&$B9)>0,"NA",AVERAGEIFS(monthly!E:E,monthly!$A:$A,">="&$A9,monthly!$B:$B,"<="&$B9)) -> NA | N9: =IF(COUNTIFS(monthly!F:F,"",monthly!$A:$A,">="&$A9,monthly!$B:$B,"<="&$B9)>0,"NA",AVERAGEIFS(monthly!F:F,monthly!$A:$A,">="&$A9,monthly!$B:$B,"<="&$B9)) -> NA | O9: =IF(COUNTIFS(monthly!G:G,"",monthly!$A:$A,">="&$A9,monthly!$B:$B,"<="&$B9)>0,"NA",AVERAGEIFS(monthly!G:G,monthly!$A:$A,">="&$A9,monthly!$B:$B,"<="&$B9)) -> 10.3 | P9: =IF(COUNTIFS(monthly!H:H,"",monthly!$A:$A,">="&$A9,monthly!$B:$B,"<="&$B9)>0,"NA",AVERAGEIFS(monthly!H:H,monthly!$A:$A,">="&$A9,monthly!$B:$B,"<="&$B9)) -> 8.7 | Q9: =IF(COUNTIFS(monthly!I:I,"",monthly!$A:$A,">="&$A9,monthly!$B:$B,"<="&$B9)>0,"NA",AVERAGEIFS(monthly!I:I,monthly!$A:$A,">="&$A9,monthly!$B:$B,"<="&$B9)) -> 1.7 | R9: =IF(COUNTIFS(monthly!J:J,"",monthly!$A:$A,">="&$A9,monthly!$B:$B,"<="&$B9)>0,"NA",AVERAGEIFS(monthly!J:J,monthly!$A:$A,">="&$A9,monthly!$B:$B,"<="&$B9)) -> NA | S9: =IF(COUNTIFS(monthly!K:K,"",monthly!$A:$A,">="&$A9,monthly!$B:$B,"<="&$B9)>0,"NA",AVERAGEIFS(monthly!K:K,monthly!$A:$A,">="&$A9,monthly!$B:$B,"<="&$B9)) -> NA | T9: =IF(COUNTIFS(monthly!L:L,"",monthly!$A:$A,">="&$A9,monthly!$B:$B,"<="&$B9)>0,"NA",AVERAGEIFS(monthly!L:L,monthly!$A:$A,">="&$A9,monthly!$B:$B,"<="&$B9)) -> 5.0548441 | U9: =IF(COUNTIFS(monthly!M:M,"",monthly!$A:$A,">="&$A9,monthly!$B:$B,"<="&$B9)>0,"NA",AVERAGEIFS(monthly!M:M,monthly!$A:$A,">="&$A9,monthly!$B:$B,"<="&$B9)) -> NA | V9: =IF(COUNTIFS(monthly!N:N,"",monthly!$A:$A,">="&$A9,monthly!$B:$B,"<="&$B9)>0,"NA",AVERAGEIFS(monthly!N:N,monthly!$A:$A,">="&$A9,monthly!$B:$B,"<="&$B9)) -> NA | W9: =IF(COUNTIFS(monthly!O:O,"",monthly!$A:$A,">="&$A9,monthly!$B:$B,"<="&$B9)>0,"NA",AVERAGEIFS(monthly!O:O,monthly!$A:$A,">="&$A9,monthly!$B:$B,"<="&$B9)) -> NA | X9: =IF(COUNTIFS(monthly!P:P,"",monthly!$A:$A,">="&$A9,monthly!$B:$B,"<="&$B9)>0,"NA",AVERAGEIFS(monthly!P:P,monthly!$A:$A,">="&$A9,monthly!$B:$B,"<="&$B9)) -> NA | Y9: =IF(COUNTIFS(monthly!Q:Q,"",monthly!$A:$A,">="&$A9,monthly!$B:$B,"<="&$B9)>0,"NA",AVERAGEIFS(monthly!Q:Q,monthly!$A:$A,">="&$A9,monthly!$B:$B,"<="&$B9)) -> 6.48 | Z9: =IF(COUNTIFS(monthly!R:R,"",monthly!$A:$A,">="&$A9,monthly!$B:$B,"<="&$B9)>0,"NA",AVERAGEIFS(monthly!R:R,monthly!$A:$A,">="&$A9,monthly!$B:$B,"<="&$B9)) -> 5.8678947 | AA9: =IF(COUNTIFS(monthly!S:S,"",monthly!$A:$A,">="&$A9,monthly!$B:$B,"<="&$B9)>0,"NA",AVERAGEIFS(monthly!S:S,monthly!$A:$A,">="&$A9,monthly!$B:$B,"<="&$B9)) -> 0.61210526 | AB9: =IF(COUNTIFS(monthly!T:T,"",monthly!$A:$A,">="&$A9,monthly!$B:$B,"<="&$B9)>0,"NA",AVERAGEIFS(monthly!T:T,monthly!$A:$A,">="&$A9,monthly!$B:$B,"<="&$B9)) -> NA | AC9: =IF(COUNTIFS(monthly!U:U,"",monthly!$A:$A,">="&$A9,monthly!$B:$B,"<="&$B9)>0,"NA",AVERAGEIFS(monthly!U:U,monthly!$A:$A,">="&$A9,monthly!$B:$B,"<="&$B9)) -> NA | AD9: =IF(COUNTIFS(monthly!V:V,"",monthly!$A:$A,">="&$A9,monthly!$B:$B,"<="&$B9)>0,"NA",AVERAGEIFS(monthly!V:V,monthly!$A:$A,">="&$A9,monthly!$B:$B,"<="&$B9)) -> NA | AE9: =IF(COUNTIFS(monthly!W:W,"",monthly!$A:$A,">="&$A9,monthly!$B:$B,"<="&$B9)>0,"NA",AVERAGEIFS(monthly!W:W,monthly!$A:$A,">="&$A9,monthly!$B:$B,"<="&$B9)) -> NA | AF9: =IF(COUNTIFS(monthly!X:X,"",monthly!$A:$A,">="&$A9,monthly!$B:$B,"<="&$B9)>0,"NA",AVERAGEIFS(monthly!X:X,monthly!$A:$A,">="&$A9,monthly!$B:$B,"<="&$B9)) -> NA | AG9: =IF(COUNTIFS(monthly!Y:Y,"",monthly!$A:$A,">="&$A9,monthly!$B:$B,"<="&$B9)>0,"NA",AVERAGEIFS(monthly!Y:Y,monthly!$A:$A,">="&$A9,monthly!$B:$B,"<="&$B9)) -> NA | AH9: =IF(COUNTIFS(monthly!Z:Z,"",monthly!$A:$A,">="&$A9,monthly!$B:$B,"<="&$B9)>0,"NA",AVERAGEIFS(monthly!Z:Z,monthly!$A:$A,">="&$A9,monthly!$B:$B,"<="&$B9)) -> NA
A10: 26299 | B10: 26388 | C10: =IF(ISBLANK(VLOOKUP($A10,quarterly_data,MATCH(C$1,quarterly!$1:$1,FALSE),FALSE)),"NA",VLOOKUP($A10,quarterly_data,MATCH(C$1,quarterly!$1:$1,FALSE),FALSE)) -> 145.50562 | D10: =IF(ISBLANK(VLOOKUP($A10,quarterly_data,MATCH(D$1,quarterly!$1:$1,FALSE),FALSE)),"NA",VLOOKUP($A10,quarterly_data,MATCH(D$1,quarterly!$1:$1,FALSE),FALSE)) -> 51.8 | E10: =IF(ISBLANK(VLOOKUP($A10,quarterly_data,MATCH(E$1,quarterly!$1:$1,FALSE),FALSE)),"NA",VLOOKUP($A10,quarterly_data,MATCH(E$1,quarterly!$1:$1,FALSE),FALSE)) -> 0.304909 | F10: =IF(ISBLANK(VLOOKUP($A10,quarterly_data,MATCH(F$1,quarterly!$1:$1,FALSE),FALSE)),"NA",VLOOKUP($A10,quarterly_data,MATCH(F$1,quarterly!$1:$1,FALSE),FALSE)) -> 0.1171435 | G10: =IF(ISBLANK(VLOOKUP($A10,quarterly_data,MATCH(G$1,quarterly!$1:$1,FALSE),FALSE)),"NA",VLOOKUP($A10,quarterly_data,MATCH(G$1,quarterly!$1:$1,FALSE),FALSE)) -> 5632.649 | H10: =IF(ISBLANK(VLOOKUP($A10,quarterly_data,MATCH(H$1,quarterly!$1:$1,FALSE),FALSE)),"NA",VLOOKUP($A10,quarterly_data,MATCH(H$1,quarterly!$1:$1,FALSE),FALSE)) -> 143900 | I10: =IF(ISBLANK(VLOOKUP($A10,quarterly_data,MATCH(I$1,quarterly!$1:$1,FALSE),FALSE)),"NA",VLOOKUP($A10,quarterly_data,MATCH(I$1,quarterly!$1:$1,FALSE),FALSE)) -> NA | J10: =IF(ISBLANK(VLOOKUP($A10,quarterly_data,MATCH(J$1,quarterly!$1:$1,FALSE),FALSE)),"NA",VLOOKUP($A10,quarterly_data,MATCH(J$1,quarterly!$1:$1,FALSE),FALSE)) -> 7.5 | K10: =IF(COUNTIFS(monthly!C:C,"",monthly!$A:$A,">="&$A10,monthly!$B:$B,"<="&$B10)>0,"NA",AVERAGEIFS(monthly!C:C,monthly!$A:$A,">="&$A10,monthly!$B:$B,"<="&$B10)) -> 98.45 | L10: =IF(COUNTIFS(monthly!D:D,"",monthly!$A:$A,">="&$A10,monthly!$B:$B,"<="&$B10)>0,"NA",AVERAGEIFS(monthly!D:D,monthly!$A:$A,">="&$A10,monthly!$B:$B,"<="&$B10)) -> 1.191 | M10: =IF(COUNTIFS(monthly!E:E,"",monthly!$A:$A,">="&$A10,monthly!$B:$B,"<="&$B10)>0,"NA",AVERAGEIFS(monthly!E:E,monthly!$A:$A,">="&$A10,monthly!$B:$B,"<="&$B10)) -> NA | N10: =IF(COUNTIFS(monthly!F:F,"",monthly!$A:$A,">="&$A10,monthly!$B:$B,"<="&$B10)>0,"NA",AVERAGEIFS(monthly!F:F,monthly!$A:$A,">="&$A10,monthly!$B:$B,"<="&$B10)) -> NA | O10: =IF(COUNTIFS(monthly!G:G,"",monthly!$A:$A,">="&$A10,monthly!$B:$B,"<="&$B10)>0,"NA",AVERAGEIFS(monthly!G:G,monthly!$A:$A,">="&$A10,monthly!$B:$B,"<="&$B10)) -> 10.3 | P10: =IF(COUNTIFS(monthly!H:H,"",monthly!$A:$A,">="&$A10,monthly!$B:$B,"<="&$B10)>0,"NA",AVERAGEIFS(monthly!H:H,monthly!$A:$A,">="&$A10,monthly!$B:$B,"<="&$B10)) -> 9.6 | Q10: =IF(COUNTIFS(monthly!I:I,"",monthly!$A:$A,">="&$A10,monthly!$B:$B,"<="&$B10)>0,"NA",AVERAGEIFS(monthly!I:I,monthly!$A:$A,">="&$A10,monthly!$B:$B,"<="&$B10)) -> 1.8 | R10: =IF(COUNTIFS(monthly!J:J,"",monthly!$A:$A,">="&$A10,monthly!$B:$B,"<="&$B10)>0,"NA",AVERAGEIFS(monthly!J:J,monthly!$A:$A,">="&$A10,monthly!$B:$B,"<="&$B10)) -> NA | S10: =IF(COUNTIFS(monthly!K:K,"",monthly!$A:$A,">="&$A10,monthly!$B:$B,"<="&$B10)>0,"NA",AVERAGEIFS(monthly!K:K,monthly!$A:$A,">="&$A10,monthly!$B:$B,"<="&$B10)) -> NA | T10: =IF(COUNTIFS(monthly!L:L,"",monthly!$A:$A,">="&$A10,monthly!$B:$B,"<="&$B10)>0,"NA",AVERAGEIFS(monthly!L:L,monthly!$A:$A,">="&$A10,monthly!$B:$B,"<="&$B10)) -> 3.4006618 | U10: =IF(COUNTIFS(monthly!M:M,"",monthly!$A:$A,">="&$A10,monthly!$B:$B,"<="&$B10)>0,"NA",AVERAGEIFS(monthly!M:M,monthly!$A:$A,">="&$A10,monthly!$B:$B,"<="&$B10)) -> NA | V10: =IF(COUNTIFS(monthly!N:N,"",monthly!$A:$A,">="&$A10,monthly!$B:$B,"<="&$B10)>0,"NA",AVERAGEIFS(monthly!N:N,monthly!$A:$A,">="&$A10,monthly!$B:$B,"<="&$B10)) -> NA | W10: =IF(COUNTIFS(monthly!O:O,"",monthly!$A:$A,">="&$A10,monthly!$B:$B,"<="&$B10)>0,"NA",AVERAGEIFS(monthly!O:O,monthly!$A:$A,">="&$A10,monthly!$B:$B,"<="&$B10)) -> NA | X10: =IF(COUNTIFS(monthly!P:P,"",monthly!$A:$A,">="&$A10,monthly!$B:$B,"<="&$B10)>0,"NA",AVERAGEIFS(monthly!P:P,monthly!$A:$A,">="&$A10,monthly!$B:$B,"<="&$B10)) -> NA | Y10: =IF(COUNTIFS(monthly!Q:Q,"",monthly!$A:$A,">="&$A10,monthly!$B:$B,"<="&$B10)>0,"NA",AVERAGEIFS(monthly!Q:Q,monthly!$A:$A,">="&$A10,monthly!$B:$B,"<="&$B10)) -> 5.99 | Z10: =IF(COUNTIFS(monthly!R:R,"",monthly!$A:$A,">="&$A10,monthly!$B:$B,"<="&$B10)>0,"NA",AVERAGEIFS(monthly!R:R,monthly!$A:$A,">="&$A10,monthly!$B:$B,"<="&$B10)) -> 6.0143095 | AA10: =IF(COUNTIFS(monthly!S:S,"",monthly!$A:$A,">="&$A10,monthly!$B:$B,"<="&$B10)>0,"NA",AVERAGEIFS(monthly!S:S,monthly!$A:$A,">="&$A10,monthly!$B:$B,"<="&$B10)) -> -0.024309524 | AB10: =IF(COUNTIFS(monthly!T:T,"",monthly!$A:$A,">="&$A10,monthly!$B:$B,"<="&$B10)>0,"NA",AVERAGEIFS(monthly!T:T,monthly!$A:$A,">="&$A10,monthly!$B:$B,"<="&$B10)) -> NA | AC10: =IF(COUNTIFS(monthly!U:U,"",monthly!$A:$A,">="&$A10,monthly!$B:$B,"<="&$B10)>0,"NA",AVERAGEIFS(monthly!U:U,monthly!$A:$A,">="&$A10,monthly!$B:$B,"<="&$B10)) -> NA | AD10: =IF(COUNTIFS(monthly!V:V,"",monthly!$A:$A,">="&$A10,monthly!$B:$B,"<="&$B10)>0,"NA",AVERAGEIFS(monthly!V:V,monthly!$A:$A,">="&$A10,monthly!$B:$B,"<="&$B10)) -> NA | AE10: =IF(COUNTIFS(monthly!W:W,"",monthly!$A:$A,">="&$A10,monthly!$B:$B,"<="&$B10)>0,"NA",AVERAGEIFS(monthly!W:W,monthly!$A:$A,">="&$A10,monthly!$B:$B,"<="&$B10)) -> NA | AF10: =IF(COUNTIFS(monthly!X:X,"",monthly!$A:$A,">="&$A10,monthly!$B:$B,"<="&$B10)>0,"NA",AVERAGEIFS(monthly!X:X,monthly!$A:$A,">="&$A10,monthly!$B:$B,"<="&$B10)) -> NA | AG10: =IF(COUNTIFS(monthly!Y:Y,"",monthly!$A:$A,">="&$A10,monthly!$B:$B,"<="&$B10)>0,"NA",AVERAGEIFS(monthly!Y:Y,monthly!$A:$A,">="&$A10,monthly!$B:$B,"<="&$B10)) -> NA | AH10: =IF(COUNTIFS(monthly!Z:Z,"",monthly!$A:$A,">="&$A10,monthly!$B:$B,"<="&$B10)>0,"NA",AVERAGEIFS(monthly!Z:Z,monthly!$A:$A,">="&$A10,monthly!$B:$B,"<="&$B10)) -> NA
A11: 26390 | B11: 26480 | C11: =IF(ISBLANK(VLOOKUP($A11,quarterly_data,MATCH(C$1,quarterly!$1:$1,FALSE),FALSE)),"NA",VLOOKUP($A11,quarterly_data,MATCH(C$1,quarterly!$1:$1,FALSE),FALSE)) -> 144.61215 | D11: =IF(ISBLANK(VLOOKUP($A11,quarterly_data,MATCH(D$1,quarterly!$1:$1,FALSE),FALSE)),"NA",VLOOKUP($A11,quarterly_data,MATCH(D$1,quarterly!$1:$1,FALSE),FALSE)) -> 53.9 | E11: =IF(ISBLANK(VLOOKUP($A11,quarterly_data,MATCH(E$1,quarterly!$1:$1,FALSE),FALSE)),"NA",VLOOKUP($A11,quarterly_data,MATCH(E$1,quarterly!$1:$1,FALSE),FALSE)) -> 0 | F11: =IF(ISBLANK(VLOOKUP($A11,quarterly_data,MATCH(F$1,quarterly!$1:$1,FALSE),FALSE)),"NA",VLOOKUP($A11,quarterly_data,MATCH(F$1,quarterly!$1:$1,FALSE),FALSE)) -> 0.0454632 | G11: =IF(ISBLANK(VLOOKUP($A11,quarterly_data,MATCH(G$1,quarterly!$1:$1,FALSE),FALSE)),"NA",VLOOKUP($A11,quarterly_data,MATCH(G$1,quarterly!$1:$1,FALSE),FALSE)) -> 5760.47 | H11: =IF(ISBLANK(VLOOKUP($A11,quarterly_data,MATCH(H$1,quarterly!$1:$1,FALSE),FALSE)),"NA",VLOOKUP($A11,quarterly_data,MATCH(H$1,quarterly!$1:$1,FALSE),FALSE)) -> 147105 | I11: =IF(ISBLANK(VLOOKUP($A11,quarterly_data,MATCH(I$1,quarterly!$1:$1,FALSE),FALSE)),"NA",VLOOKUP($A11,quarterly_data,MATCH(I$1,quarterly!$1:$1,FALSE),FALSE)) -> NA | J11: =IF(ISBLANK(VLOOKUP($A11,quarterly_data,MATCH(J$1,quarterly!$1:$1,FALSE),FALSE)),"NA",VLOOKUP($A11,quarterly_data,MATCH(J$1,quarterly!$1:$1,FALSE),FALSE)) -> 7.58 | K11: =IF(COUNTIFS(monthly!C:C,"",monthly!$A:$A,">="&$A11,monthly!$B:$B,"<="&$B11)>0,"NA",AVERAGEIFS(monthly!C:C,monthly!$A:$A,">="&$A11,monthly!$B:$B,"<="&$B11)) -> 98.1 | L11: =IF(COUNTIFS(monthly!D:D,"",monthly!$A:$A,">="&$A11,monthly!$B:$B,"<="&$B11)>0,"NA",AVERAGEIFS(monthly!D:D,monthly!$A:$A,">="&$A11,monthly!$B:$B,"<="&$B11)) -> 1.191 | M11: =IF(COUNTIFS(monthly!E:E,"",monthly!$A:$A,">="&$A11,monthly!$B:$B,"<="&$B11)>0,"NA",AVERAGEIFS(monthly!E:E,monthly!$A:$A,">="&$A11,monthly!$B:$B,"<="&$B11)) -> NA | N11: =IF(COUNTIFS(monthly!F:F,"",monthly!$A:$A,">="&$A11,monthly!$B:$B,"<="&$B11)>0,"NA",AVERAGEIFS(monthly!F:F,monthly!$A:$A,">="&$A11,monthly!$B:$B,"<="&$B11)) -> NA | O11: =IF(COUNTIFS(monthly!G:G,"",monthly!$A:$A,">="&$A11,monthly!$B:$B,"<="&$B11)>0,"NA",AVERAGEIFS(monthly!G:G,monthly!$A:$A,">="&$A11,monthly!$B:$B,"<="&$B11)) -> 10.3 | P11: =IF(COUNTIFS(monthly!H:H,"",monthly!$A:$A,">="&$A11,monthly!$B:$B,"<="&$B11)>0,"NA",AVERAGEIFS(monthly!H:H,monthly!$A:$A,">="&$A11,monthly!$B:$B,"<="&$B11)) -> 9.6 | Q11: =IF(COUNTIFS(monthly!I:I,"",monthly!$A:$A,">="&$A11,monthly!$B:$B,"<="&$B11)>0,"NA",AVERAGEIFS(monthly!I:I,monthly!$A:$A,">="&$A11,monthly!$B:$B,"<="&$B11)) -> 1.8 | R11: =IF(COUNTIFS(monthly!J:J,"",monthly!$A:$A,">="&$A11,monthly!$B:$B,"<="&$B11)>0,"NA",AVERAGEIFS(monthly!J:J,monthly!$A:$A,">="&$A11,monthly!$B:$B,"<="&$B11)) -> NA | S11: =IF(COUNTIFS(monthly!K:K,"",monthly!$A:$A,">="&$A11,monthly!$B:$B,"<="&$B11)>0,"NA",AVERAGEIFS(monthly!K:K,monthly!$A:$A,">="&$A11,monthly!$B:$B,"<="&$B11)) -> NA | T11: =IF(COUNTIFS(monthly!L:L,"",monthly!$A:$A,">="&$A11,monthly!$B:$B,"<="&$B11)>0,"NA",AVERAGEIFS(monthly!L:L,monthly!$A:$A,">="&$A11,monthly!$B:$B,"<="&$B11)) -> 4.3017814 | U11: =IF(COUNTIFS(monthly!M:M,"",monthly!$A:$A,">="&$A11,monthly!$B:$B,"<="&$B11)>0,"NA",AVERAGEIFS(monthly!M:M,monthly!$A:$A,">="&$A11,monthly!$B:$B,"<="&$B11)) -> NA | V11: =IF(COUNTIFS(monthly!N:N,"",monthly!$A:$A,">="&$A11,monthly!$B:$B,"<="&$B11)>0,"NA",AVERAGEIFS(monthly!N:N,monthly!$A:$A,">="&$A11,monthly!$B:$B,"<="&$B11)) -> NA | W11: =IF(COUNTIFS(monthly!O:O,"",monthly!$A:$A,">="&$A11,monthly!$B:$B,"<="&$B11)>0,"NA",AVERAGEIFS(monthly!O:O,monthly!$A:$A,">="&$A11,monthly!$B:$B,"<="&$B11)) -> NA | X11: =IF(COUNTIFS(monthly!P:P,"",monthly!$A:$A,">="&$A11,monthly!$B:$B,"<="&$B11)>0,"NA",AVERAGEIFS(monthly!P:P,monthly!$A:$A,">="&$A11,monthly!$B:$B,"<="&$B11)) -> NA | Y11: =IF(COUNTIFS(monthly!Q:Q,"",monthly!$A:$A,">="&$A11,monthly!$B:$B,"<="&$B11)>0,"NA",AVERAGEIFS(monthly!Q:Q,monthly!$A:$A,">="&$A11,monthly!$B:$B,"<="&$B11)) -> 5.85 | Z11: =IF(COUNTIFS(monthly!R:R,"",monthly!$A:$A,">="&$A11,monthly!$B:$B,"<="&$B11)>0,"NA",AVERAGEIFS(monthly!R:R,monthly!$A:$A,">="&$A11,monthly!$B:$B,"<="&$B11)) -> 6.1425606 | AA11: =IF(COUNTIFS(monthly!S:S,"",monthly!$A:$A,">="&$A11,monthly!$B:$B,"<="&$B11)>0,"NA",AVERAGEIFS(monthly!S:S,monthly!$A:$A,">="&$A11,monthly!$B:$B,"<="&$B11)) -> -0.29256061 | AB11: =IF(COUNTIFS(monthly!T:T,"",monthly!$A:$A,">="&$A11,monthly!$B:$B,"<="&$B11)>0,"NA",AVERAGEIFS(monthly!T:T,monthly!$A:$A,">="&$A11,monthly!$B:$B,"<="&$B11)) -> NA | AC11: =IF(COUNTIFS(monthly!U:U,"",monthly!$A:$A,">="&$A11,monthly!$B:$B,"<="&$B11)>0,"NA",AVERAGEIFS(monthly!U:U,monthly!$A:$A,">="&$A11,monthly!$B:$B,"<="&$B11)) -> NA | AD11: =IF(COUNTIFS(monthly!V:V,"",monthly!$A:$A,">="&$A11,monthly!$B:$B,"<="&$B11)>0,"NA",AVERAGEIFS(monthly!V:V,monthly!$A:$A,">="&$A11,monthly!$B:$B,"<="&$B11)) -> NA | AE11: =IF(COUNTIFS(monthly!W:W,"",monthly!$A:$A,">="&$A11,monthly!$B:$B,"<="&$B11)>0,"NA",AVERAGEIFS(monthly!W:W,monthly!$A:$A,">="&$A11,monthly!$B:$B,"<="&$B11)) -> NA | AF11: =IF(COUNTIFS(monthly!X:X,"",monthly!$A:$A,">="&$A11,monthly!$B:$B,"<="&$B11)>0,"NA",AVERAGEIFS(monthly!X:X,monthly!$A:$A,">="&$A11,monthly!$B:$B,"<="&$B11)) -> NA | AG11: =IF(COUNTIFS(monthly!Y:Y,"",monthly!$A:$A,">="&$A11,monthly!$B:$B,"<="&$B11)>0,"NA",AVERAGEIFS(monthly!Y:Y,monthly!$A:$A,">="&$A11,monthly!$B:$B,"<="&$B11)) -> NA | AH11: =IF(COUNTIFS(monthly!Z:Z,"",monthly!$A:$A,">="&$A11,monthly!$B:$B,"<="&$B11)>0,"NA",AVERAGEIFS(monthly!Z:Z,monthly!$A:$A,">="&$A11,monthly!$B:$B,"<="&$B11)) -> NA
A12: 26481 | B12: 26572 | C12: =IF(ISBLANK(VLOOKUP($A12,quarterly_data,MATCH(C$1,quarterly!$1:$1,FALSE),FALSE)),"NA",VLOOKUP($A12,quarterly_data,MATCH(C$1,quarterly!$1:$1,FALSE),FALSE)) -> 143.92313 | D12: =IF(ISBLANK(VLOOKUP($A12,quarterly_data,MATCH(D$1,quarterly!$1:$1,FALSE),FALSE)),"NA",VLOOKUP($A12,quarterly_data,MATCH(D$1,quarterly!$1:$1,FALSE),FALSE)) -> 56.9 | E12: =IF(ISBLANK(VLOOKUP($A12,quarterly_data,MATCH(E$1,quarterly!$1:$1,FALSE),FALSE)),"NA",VLOOKUP($A12,quarterly_data,MATCH(E$1,quarterly!$1:$1,FALSE),FALSE)) -> 0.373925 | F12: =IF(ISBLANK(VLOOKUP($A12,quarterly_data,MATCH(F$1,quarterly!$1:$1,FALSE),FALSE)),"NA",VLOOKUP($A12,quarterly_data,MATCH(F$1,quarterly!$1:$1,FALSE),FALSE)) -> 0.0849486 | G12: =IF(ISBLANK(VLOOKUP($A12,quarterly_data,MATCH(G$1,quarterly!$1:$1,FALSE),FALSE)),"NA",VLOOKUP($A12,quarterly_data,MATCH(G$1,quarterly!$1:$1,FALSE),FALSE)) -> 5814.854 | H12: =IF(ISBLANK(VLOOKUP($A12,quarterly_data,MATCH(H$1,quarterly!$1:$1,FALSE),FALSE)),"NA",VLOOKUP($A12,quarterly_data,MATCH(H$1,quarterly!$1:$1,FALSE),FALSE)) -> 146356 | I12: =IF(ISBLANK(VLOOKUP($A12,quarterly_data,MATCH(I$1,quarterly!$1:$1,FALSE),FALSE)),"NA",VLOOKUP($A12,quarterly_data,MATCH(I$1,quarterly!$1:$1,FALSE),FALSE)) -> NA | J12: =IF(ISBLANK(VLOOKUP($A12,quarterly_data,MATCH(J$1,quarterly!$1:$1,FALSE),FALSE)),"NA",VLOOKUP($A12,quarterly_data,MATCH(J$1,quarterly!$1:$1,FALSE),FALSE)) -> 7.69 | K12: =IF(COUNTIFS(monthly!C:C,"",monthly!$A:$A,">="&$A12,monthly!$B:$B,"<="&$B12)>0,"NA",AVERAGEIFS(monthly!C:C,monthly!$A:$A,">="&$A12,monthly!$B:$B,"<="&$B12)) -> 98.666667 | L12: =IF(COUNTIFS(monthly!D:D,"",monthly!$A:$A,">="&$A12,monthly!$B:$B,"<="&$B12)>0,"NA",AVERAGEIFS(monthly!D:D,monthly!$A:$A,">="&$A12,monthly!$B:$B,"<="&$B12)) -> 1.191 | M12: =IF(COUNTIFS(monthly!E:E,"",monthly!$A:$A,">="&$A12,monthly!$B:$B,"<="&$B12)>0,"NA",AVERAGEIFS(monthly!E:E,monthly!$A:$A,">="&$A12,monthly!$B:$B,"<="&$B12)) -> NA | N12: =IF(COUNTIFS(monthly!F:F,"",monthly!$A:$A,">="&$A12,monthly!$B:$B,"<="&$B12)>0,"NA",AVERAGEIFS(monthly!F:F,monthly!$A:$A,">="&$A12,monthly!$B:$B,"<="&$B12)) -> NA | O12: =IF(COUNTIFS(monthly!G:G,"",monthly!$A:$A,">="&$A12,monthly!$B:$B,"<="&$B12)>0,"NA",AVERAGEIFS(monthly!G:G,monthly!$A:$A,">="&$A12,monthly!$B:$B,"<="&$B12)) -> 10.3 | P12: =IF(COUNTIFS(monthly!H:H,"",monthly!$A:$A,">="&$A12,monthly!$B:$B,"<="&$B12)>0,"NA",AVERAGEIFS(monthly!H:H,monthly!$A:$A,">="&$A12,monthly!$B:$B,"<="&$B12)) -> 9.6 | Q12: =IF(COUNTIFS(monthly!I:I,"",monthly!$A:$A,">="&$A12,monthly!$B:$B,"<="&$B12)>0,"NA",AVERAGEIFS(monthly!I:I,monthly!$A:$A,">="&$A12,monthly!$B:$B,"<="&$B12)) -> 1.9 | R12: =IF(COUNTIFS(monthly!J:J,"",monthly!$A:$A,">="&$A12,monthly!$B:$B,"<="&$B12)>0,"NA",AVERAGEIFS(monthly!J:J,monthly!$A:$A,">="&$A12,monthly!$B:$B,"<="&$B12)) -> NA | S12: =IF(COUNTIFS(monthly!K:K,"",monthly!$A:$A,">="&$A12,monthly!$B:$B,"<="&$B12)>0,"NA",AVERAGEIFS(monthly!K:K,monthly!$A:$A,">="&$A12,monthly!$B:$B,"<="&$B12)) -> NA | T12: =IF(COUNTIFS(monthly!L:L,"",monthly!$A:$A,">="&$A12,monthly!$B:$B,"<="&$B12)>0,"NA",AVERAGEIFS(monthly!L:L,monthly!$A:$A,">="&$A12,monthly!$B:$B,"<="&$B12)) -> 4.7428423 | U12: =IF(COUNTIFS(monthly!M:M,"",monthly!$A:$A,">="&$A12,monthly!$B:$B,"<="&$B12)>0,"NA",AVERAGEIFS(monthly!M:M,monthly!$A:$A,">="&$A12,monthly!$B:$B,"<="&$B12)) -> NA | V12: =IF(COUNTIFS(monthly!N:N,"",monthly!$A:$A,">="&$A12,monthly!$B:$B,"<="&$B12)>0,"NA",AVERAGEIFS(monthly!N:N,monthly!$A:$A,">="&$A12,monthly!$B:$B,"<="&$B12)) -> NA | W12: =IF(COUNTIFS(monthly!O:O,"",monthly!$A:$A,">="&$A12,monthly!$B:$B,"<="&$B12)>0,"NA",AVERAGEIFS(monthly!O:O,monthly!$A:$A,">="&$A12,monthly!$B:$B,"<="&$B12)) -> NA | X12: =IF(COUNTIFS(monthly!P:P,"",monthly!$A:$A,">="&$A12,monthly!$B:$B,"<="&$B12)>0,"NA",AVERAGEIFS(monthly!P:P,monthly!$A:$A,">="&$A12,monthly!$B:$B,"<="&$B12)) -> NA | Y12: =IF(COUNTIFS(monthly!Q:Q,"",monthly!$A:$A,">="&$A12,monthly!$B:$B,"<="&$B12)>0,"NA",AVERAGEIFS(monthly!Q:Q,monthly!$A:$A,">="&$A12,monthly!$B:$B,"<="&$B12)) -> 5.7666667 | Z12: =IF(COUNTIFS(monthly!R:R,"",monthly!$A:$A,">="&$A12,monthly!$B:$B,"<="&$B12)>0,"NA",AVERAGEIFS(monthly!R:R,monthly!$A:$A,">="&$A12,monthly!$B:$B,"<="&$B12)) -> 6.2909783 | AA12: =IF(COUNTIFS(monthly!S:S,"",monthly!$A:$A,">="&$A12,monthly!$B:$B,"<="&$B12)>0,"NA",AVERAGEIFS(monthly!S:S,monthly!$A:$A,">="&$A12,monthly!$B:$B,"<="&$B12)) -> -0.52431159 | AB12: =IF(COUNTIFS(monthly!T:T,"",monthly!$A:$A,">="&$A12,monthly!$B:$B,"<="&$B12)>0,"NA",AVERAGEIFS(monthly!T:T,monthly!$A:$A,">="&$A12,monthly!$B:$B,"<="&$B12)) -> NA | AC12: =IF(COUNTIFS(monthly!U:U,"",monthly!$A:$A,">="&$A12,monthly!$B:$B,"<="&$B12)>0,"NA",AVERAGEIFS(monthly!U:U,monthly!$A:$A,">="&$A12,monthly!$B:$B,"<="&$B12)) -> NA | AD12: =IF(COUNTIFS(monthly!V:V,"",monthly!$A:$A,">="&$A12,monthly!$B:$B,"<="&$B12)>0,"NA",AVERAGEIFS(monthly!V:V,monthly!$A:$A,">="&$A12,monthly!$B:$B,"<="&$B12)) -> NA | AE12: =IF(COUNTIFS(monthly!W:W,"",monthly!$A:$A,">="&$A12,monthly!$B:$B,"<="&$B12)>0,"NA",AVERAGEIFS(monthly!W:W,monthly!$A:$A,">="&$A12,monthly!$B:$B,"<="&$B12)) -> NA | AF12: =IF(COUNTIFS(monthly!X:X,"",monthly!$A:$A,">="&$A12,monthly!$B:$B,"<="&$B12)>0,"NA",AVERAGEIFS(monthly!X:X,monthly!$A:$A,">="&$A12,monthly!$B:$B,"<="&$B12)) -> NA | AG12: =IF(COUNTIFS(monthly!Y:Y,"",monthly!$A:$A,">="&$A12,monthly!$B:$B,"<="&$B12)>0,"NA",AVERAGEIFS(monthly!Y:Y,monthly!$A:$A,">="&$A12,monthly!$B:$B,"<="&$B12)) -> NA | AH12: =IF(COUNTIFS(monthly!Z:Z,"",monthly!$A:$A,">="&$A12,monthly!$B:$B,"<="&$B12)>0,"NA",AVERAGEIFS(monthly!Z:Z,monthly!$A:$A,">="&$A12,monthly!$B:$B,"<="&$B12)) -> NA
A13: 26573 | B13: 26663 | C13: =IF(ISBLANK(VLOOKUP($A13,quarterly_data,MATCH(C$1,quarterly!$1:$1,FALSE),FALSE)),"NA",VLOOKUP($A13,quarterly_data,MATCH(C$1,quarterly!$1:$1,FALSE),FALSE)) -> 144.52606 | D13: =IF(ISBLANK(VLOOKUP($A13,quarterly_data,MATCH(D$1,quarterly!$1:$1,FALSE),FALSE)),"NA",VLOOKUP($A13,quarterly_data,MATCH(D$1,quarterly!$1:$1,FALSE),FALSE)) -> 58 | E13: =IF(ISBLANK(VLOOKUP($A13,quarterly_data,MATCH(E$1,quarterly!$1:$1,FALSE),FALSE)),"NA",VLOOKUP($A13,quarterly_data,MATCH(E$1,quarterly!$1:$1,FALSE),FALSE)) -> 0 | F13: =IF(ISBLANK(VLOOKUP($A13,quarterly_data,MATCH(F$1,quarterly!$1:$1,FALSE),FALSE)),"NA",VLOOKUP($A13,quarterly_data,MATCH(F$1,quarterly!$1:$1,FALSE),FALSE)) -> 0.0373925 | G13: =IF(ISBLANK(VLOOKUP($A13,quarterly_data,MATCH(G$1,quarterly!$1:$1,FALSE),FALSE)),"NA",VLOOKUP($A13,quarterly_data,MATCH(G$1,quarterly!$1:$1,FALSE),FALSE)) -> 5912.22 | H13: =IF(ISBLANK(VLOOKUP($A13,quarterly_data,MATCH(H$1,quarterly!$1:$1,FALSE),FALSE)),"NA",VLOOKUP($A13,quarterly_data,MATCH(H$1,quarterly!$1:$1,FALSE),FALSE)) -> 147885 | I13: =IF(ISBLANK(VLOOKUP($A13,quarterly_data,MATCH(I$1,quarterly!$1:$1,FALSE),FALSE)),"NA",VLOOKUP($A13,quarterly_data,MATCH(I$1,quarterly!$1:$1,FALSE),FALSE)) -> NA | J13: =IF(ISBLANK(VLOOKUP($A13,quarterly_data,MATCH(J$1,quarterly!$1:$1,FALSE),FALSE)),"NA",VLOOKUP($A13,quarterly_data,MATCH(J$1,quarterly!$1:$1,FALSE),FALSE)) -> 7.77 | K13: =IF(COUNTIFS(monthly!C:C,"",monthly!$A:$A,">="&$A13,monthly!$B:$B,"<="&$B13)>0,"NA",AVERAGEIFS(monthly!C:C,monthly!$A:$A,">="&$A13,monthly!$B:$B,"<="&$B13)) -> 99.6 | L13: =IF(COUNTIFS(monthly!D:D,"",monthly!$A:$A,">="&$A13,monthly!$B:$B,"<="&$B13)>0,"NA",AVERAGEIFS(monthly!D:D,monthly!$A:$A,">="&$A13,monthly!$B:$B,"<="&$B13)) -> 1.191 | M13: =IF(COUNTIFS(monthly!E:E,"",monthly!$A:$A,">="&$A13,monthly!$B:$B,"<="&$B13)>0,"NA",AVERAGEIFS(monthly!E:E,monthly!$A:$A,">="&$A13,monthly!$B:$B,"<="&$B13)) -> NA | N13: =IF(COUNTIFS(monthly!F:F,"",monthly!$A:$A,">="&$A13,monthly!$B:$B,"<="&$B13)>0,"NA",AVERAGEIFS(monthly!F:F,monthly!$A:$A,">="&$A13,monthly!$B:$B,"<="&$B13)) -> NA | O13: =IF(COUNTIFS(monthly!G:G,"",monthly!$A:$A,">="&$A13,monthly!$B:$B,"<="&$B13)>0,"NA",AVERAGEIFS(monthly!G:G,monthly!$A:$A,">="&$A13,monthly!$B:$B,"<="&$B13)) -> 10.3 | P13: =IF(COUNTIFS(monthly!H:H,"",monthly!$A:$A,">="&$A13,monthly!$B:$B,"<="&$B13)>0,"NA",AVERAGEIFS(monthly!H:H,monthly!$A:$A,">="&$A13,monthly!$B:$B,"<="&$B13)) -> 9.6 | Q13: =IF(COUNTIFS(monthly!I:I,"",monthly!$A:$A,">="&$A13,monthly!$B:$B,"<="&$B13)>0,"NA",AVERAGEIFS(monthly!I:I,monthly!$A:$A,">="&$A13,monthly!$B:$B,"<="&$B13)) -> 1.9 | R13: =IF(COUNTIFS(monthly!J:J,"",monthly!$A:$A,">="&$A13,monthly!$B:$B,"<="&$B13)>0,"NA",AVERAGEIFS(monthly!J:J,monthly!$A:$A,">="&$A13,monthly!$B:$B,"<="&$B13)) -> NA | S13: =IF(COUNTIFS(monthly!K:K,"",monthly!$A:$A,">="&$A13,monthly!$B:$B,"<="&$B13)>0,"NA",AVERAGEIFS(monthly!K:K,monthly!$A:$A,">="&$A13,monthly!$B:$B,"<="&$B13)) -> NA | T13: =IF(COUNTIFS(monthly!L:L,"",monthly!$A:$A,">="&$A13,monthly!$B:$B,"<="&$B13)>0,"NA",AVERAGEIFS(monthly!L:L,monthly!$A:$A,">="&$A13,monthly!$B:$B,"<="&$B13)) -> 5.0507473 | U13: =IF(COUNTIFS(monthly!M:M,"",monthly!$A:$A,">="&$A13,monthly!$B:$B,"<="&$B13)>0,"NA",AVERAGEIFS(monthly!M:M,monthly!$A:$A,">="&$A13,monthly!$B:$B,"<="&$B13)) -> NA | V13: =IF(COUNTIFS(monthly!N:N,"",monthly!$A:$A,">="&$A13,monthly!$B:$B,"<="&$B13)>0,"NA",AVERAGEIFS(monthly!N:N,monthly!$A:$A,">="&$A13,monthly!$B:$B,"<="&$B13)) -> NA | W13: =IF(COUNTIFS(monthly!O:O,"",monthly!$A:$A,">="&$A13,monthly!$B:$B,"<="&$B13)>0,"NA",AVERAGEIFS(monthly!O:O,monthly!$A:$A,">="&$A13,monthly!$B:$B,"<="&$B13)) -> NA | X13: =IF(COUNTIFS(monthly!P:P,"",monthly!$A:$A,">="&$A13,monthly!$B:$B,"<="&$B13)>0,"NA",AVERAGEIFS(monthly!P:P,monthly!$A:$A,">="&$A13,monthly!$B:$B,"<="&$B13)) -> NA | Y13: =IF(COUNTIFS(monthly!Q:Q,"",monthly!$A:$A,">="&$A13,monthly!$B:$B,"<="&$B13)>0,"NA",AVERAGEIFS(monthly!Q:Q,monthly!$A:$A,">="&$A13,monthly!$B:$B,"<="&$B13)) -> 5.765 | Z13: =IF(COUNTIFS(monthly!R:R,"",monthly!$A:$A,">="&$A13,monthly!$B:$B,"<="&$B13)>0,"NA",AVERAGEIFS(monthly!R:R,monthly!$A:$A,">="&$A13,monthly!$B:$B,"<="&$B13)) -> 6.38 | AA13: =IF(COUNTIFS(monthly!S:S,"",monthly!$A:$A,">="&$A13,monthly!$B:$B,"<="&$B13)>0,"NA",AVERAGEIFS(monthly!S:S,monthly!$A:$A,">="&$A13,monthly!$B:$B,"<="&$B13)) -> -0.615 | AB13: =IF(COUNTIFS(monthly!T:T,"",monthly!$A:$A,">="&$A13,monthly!$B:$B,"<="&$B13)>0,"NA",AVERAGEIFS(monthly!T:T,monthly!$A:$A,">="&$A13,monthly!$B:$B,"<="&$B13)) -> NA | AC13: =IF(COUNTIFS(monthly!U:U,"",monthly!$A:$A,">="&$A13,monthly!$B:$B,"<="&$B13)>0,"NA",AVERAGEIFS(monthly!U:U,monthly!$A:$A,">="&$A13,monthly!$B:$B,"<="&$B13)) -> NA | AD13: =IF(COUNTIFS(monthly!V:V,"",monthly!$A:$A,">="&$A13,monthly!$B:$B,"<="&$B13)>0,"NA",AVERAGEIFS(monthly!V:V,monthly!$A:$A,">="&$A13,monthly!$B:$B,"<="&$B13)) -> NA | AE13: =IF(COUNTIFS(monthly!W:W,"",monthly!$A:$A,">="&$A13,monthly!$B:$B,"<="&$B13)>0,"NA",AVERAGEIFS(monthly!W:W,monthly!$A:$A,">="&$A13,monthly!$B:$B,"<="&$B13)) -> NA | AF13: =IF(COUNTIFS(monthly!X:X,"",monthly!$A:$A,">="&$A13,monthly!$B:$B,"<="&$B13)>0,"NA",AVERAGEIFS(monthly!X:X,monthly!$A:$A,">="&$A13,monthly!$B:$B,"<="&$B13)) -> NA | AG13: =IF(COUNTIFS(monthly!Y:Y,"",monthly!$A:$A,">="&$A13,monthly!$B:$B,"<="&$B13)>0,"NA",AVERAGEIFS(monthly!Y:Y,monthly!$A:$A,">="&$A13,monthly!$B:$B,"<="&$B13)) -> NA | AH13: =IF(COUNTIFS(monthly!Z:Z,"",monthly!$A:$A,">="&$A13,monthly!$B:$B,"<="&$B13)>0,"NA",AVERAGEIFS(monthly!Z:Z,monthly!$A:$A,">="&$A13,monthly!$B:$B,"<="&$B13)) -> NA
... A227: 46113 | B227: 46203 | C227: =IF(ISBLANK(VLOOKUP($A227,quarterly_data,MATCH(C$1,quarterly!$1:$1,FALSE),FALSE)),"NA",VLOOKUP($A227,quarterly_data,MATCH(C$1,quarterly!$1:$1,FALSE),FALSE)) -> 157.31891 | D227: =IF(ISBLANK(VLOOKUP($A227,quarterly_data,MATCH(D$1,quarterly!$1:$1,FALSE),FALSE)),"NA",VLOOKUP($A227,quarterly_data,MATCH(D$1,quarterly!$1:$1,FALSE),FALSE)) -> 94.8 | E227: =IF(ISBLANK(VLOOKUP($A227,quarterly_data,MATCH(E$1,quarterly!$1:$1,FALSE),FALSE)),"NA",VLOOKUP($A227,quarterly_data,MATCH(E$1,quarterly!$1:$1,FALSE),FALSE)) -> 0.0850123 | F227: =IF(ISBLANK(VLOOKUP($A227,quarterly_data,MATCH(F$1,quarterly!$1:$1,FALSE),FALSE)),"NA",VLOOKUP($A227,quarterly_data,MATCH(F$1,quarterly!$1:$1,FALSE),FALSE)) -> 0.0401574 | G227: =IF(ISBLANK(VLOOKUP($A227,quarterly_data,MATCH(G$1,quarterly!$1:$1,FALSE),FALSE)),"NA",VLOOKUP($A227,quarterly_data,MATCH(G$1,quarterly!$1:$1,FALSE),FALSE)) -> 24269.613 | H227: =IF(ISBLANK(VLOOKUP($A227,quarterly_data,MATCH(H$1,quarterly!$1:$1,FALSE),FALSE)),"NA",VLOOKUP($A227,quarterly_data,MATCH(H$1,quarterly!$1:$1,FALSE),FALSE)) -> 699461 | I227: =IF(ISBLANK(VLOOKUP($A227,quarterly_data,MATCH(I$1,quarterly!$1:$1,FALSE),FALSE)),"NA",VLOOKUP($A227,quarterly_data,MATCH(I$1,quarterly!$1:$1,FALSE),FALSE)) -> 0.8 | J227: =IF(ISBLANK(VLOOKUP($A227,quarterly_data,MATCH(J$1,quarterly!$1:$1,FALSE),FALSE)),"NA",VLOOKUP($A227,quarterly_data,MATCH(J$1,quarterly!$1:$1,FALSE),FALSE)) -> 102.31 | K227: =IF(COUNTIFS(monthly!C:C,"",monthly!$A:$A,">="&$A227,monthly!$B:$B,"<="&$B227)>0,"NA",AVERAGEIFS(monthly!C:C,monthly!$A:$A,">="&$A227,monthly!$B:$B,"<="&$B227)) -> 65.833333 | L227: =IF(COUNTIFS(monthly!D:D,"",monthly!$A:$A,">="&$A227,monthly!$B:$B,"<="&$B227)>0,"NA",AVERAGEIFS(monthly!D:D,monthly!$A:$A,">="&$A227,monthly!$B:$B,"<="&$B227)) -> 0.70486667 | M227: =IF(COUNTIFS(monthly!E:E,"",monthly!$A:$A,">="&$A227,monthly!$B:$B,"<="&$B227)>0,"NA",AVERAGEIFS(monthly!E:E,monthly!$A:$A,">="&$A227,monthly!$B:$B,"<="&$B227)) -> 111.8443 | N227: =IF(COUNTIFS(monthly!F:F,"",monthly!$A:$A,">="&$A227,monthly!$B:$B,"<="&$B227)>0,"NA",AVERAGEIFS(monthly!F:F,monthly!$A:$A,">="&$A227,monthly!$B:$B,"<="&$B227)) -> 113.64615 | O227: =IF(COUNTIFS(monthly!G:G,"",monthly!$A:$A,">="&$A227,monthly!$B:$B,"<="&$B227)>0,"NA",AVERAGEIFS(monthly!G:G,monthly!$A:$A,">="&$A227,monthly!$B:$B,"<="&$B227)) -> 105.16667 | P227: =IF(COUNTIFS(monthly!H:H,"",monthly!$A:$A,">="&$A227,monthly!$B:$B,"<="&$B227)>0,"NA",AVERAGEIFS(monthly!H:H,monthly!$A:$A,">="&$A227,monthly!$B:$B,"<="&$B227)) -> 135.43333 | Q227: =IF(COUNTIFS(monthly!I:I,"",monthly!$A:$A,">="&$A227,monthly!$B:$B,"<="&$B227)>0,"NA",AVERAGEIFS(monthly!I:I,monthly!$A:$A,">="&$A227,monthly!$B:$B,"<="&$B227)) -> 104.43333 | R227: =IF(COUNTIFS(monthly!J:J,"",monthly!$A:$A,">="&$A227,monthly!$B:$B,"<="&$B227)>0,"NA",AVERAGEIFS(monthly!J:J,monthly!$A:$A,">="&$A227,monthly!$B:$B,"<="&$B227)) -> 13.44 | S227: =IF(COUNTIFS(monthly!K:K,"",monthly!$A:$A,">="&$A227,monthly!$B:$B,"<="&$B227)>0,"NA",AVERAGEIFS(monthly!K:K,monthly!$A:$A,">="&$A227,monthly!$B:$B,"<="&$B227)) -> 4.2533333 | T227: =IF(COUNTIFS(monthly!L:L,"",monthly!$A:$A,">="&$A227,monthly!$B:$B,"<="&$B227)>0,"NA",AVERAGEIFS(monthly!L:L,monthly!$A:$A,">="&$A227,monthly!$B:$B,"<="&$B227)) -> 3.6310251 | U227: =IF(COUNTIFS(monthly!M:M,"",monthly!$A:$A,">="&$A227,monthly!$B:$B,"<="&$B227)>0,"NA",AVERAGEIFS(monthly!M:M,monthly!$A:$A,">="&$A227,monthly!$B:$B,"<="&$B227)) -> 0.62230824 | V227: =IF(COUNTIFS(monthly!N:N,"",monthly!$A:$A,">="&$A227,monthly!$B:$B,"<="&$B227)>0,"NA",AVERAGEIFS(monthly!N:N,monthly!$A:$A,">="&$A227,monthly!$B:$B,"<="&$B227)) -> 4.606 | W227: =IF(COUNTIFS(monthly!O:O,"",monthly!$A:$A,">="&$A227,monthly!$B:$B,"<="&$B227)>0,"NA",AVERAGEIFS(monthly!O:O,monthly!$A:$A,">="&$A227,monthly!$B:$B,"<="&$B227)) -> 3.9689827 | X227: =IF(COUNTIFS(monthly!P:P,"",monthly!$A:$A,">="&$A227,monthly!$B:$B,"<="&$B227)>0,"NA",AVERAGEIFS(monthly!P:P,monthly!$A:$A,">="&$A227,monthly!$B:$B,"<="&$B227)) -> 0.63701732 | Y227: =IF(COUNTIFS(monthly!Q:Q,"",monthly!$A:$A,">="&$A227,monthly!$B:$B,"<="&$B227)>0,"NA",AVERAGEIFS(monthly!Q:Q,monthly!$A:$A,">="&$A227,monthly!$B:$B,"<="&$B227)) -> 4.9273333 | Z227: =IF(COUNTIFS(monthly!R:R,"",monthly!$A:$A,">="&$A227,monthly!$B:$B,"<="&$B227)>0,"NA",AVERAGEIFS(monthly!R:R,monthly!$A:$A,">="&$A227,monthly!$B:$B,"<="&$B227)) -> 4.4245224 | AA227: =IF(COUNTIFS(monthly!S:S,"",monthly!$A:$A,">="&$A227,monthly!$B:$B,"<="&$B227)>0,"NA",AVERAGEIFS(monthly!S:S,monthly!$A:$A,">="&$A227,monthly!$B:$B,"<="&$B227)) -> 0.50281097 | AB227: =IF(COUNTIFS(monthly!T:T,"",monthly!$A:$A,">="&$A227,monthly!$B:$B,"<="&$B227)>0,"NA",AVERAGEIFS(monthly!T:T,monthly!$A:$A,">="&$A227,monthly!$B:$B,"<="&$B227)) -> 18.318622 | AC227: =IF(COUNTIFS(monthly!U:U,"",monthly!$A:$A,">="&$A227,monthly!$B:$B,"<="&$B227)>0,"NA",AVERAGEIFS(monthly!U:U,monthly!$A:$A,">="&$A227,monthly!$B:$B,"<="&$B227)) -> 315.57953 | AD227: =IF(COUNTIFS(monthly!V:V,"",monthly!$A:$A,">="&$A227,monthly!$B:$B,"<="&$B227)>0,"NA",AVERAGEIFS(monthly!V:V,monthly!$A:$A,">="&$A227,monthly!$B:$B,"<="&$B227)) -> 297.91141 | AE227: =IF(COUNTIFS(monthly!W:W,"",monthly!$A:$A,">="&$A227,monthly!$B:$B,"<="&$B227)>0,"NA",AVERAGEIFS(monthly!W:W,monthly!$A:$A,">="&$A227,monthly!$B:$B,"<="&$B227)) -> 211.26911 | AF227: =IF(COUNTIFS(monthly!X:X,"",monthly!$A:$A,">="&$A227,monthly!$B:$B,"<="&$B227)>0,"NA",AVERAGEIFS(monthly!X:X,monthly!$A:$A,">="&$A227,monthly!$B:$B,"<="&$B227)) -> 239.01214 | AG227: =IF(COUNTIFS(monthly!Y:Y,"",monthly!$A:$A,">="&$A227,monthly!$B:$B,"<="&$B227)>0,"NA",AVERAGEIFS(monthly!Y:Y,monthly!$A:$A,">="&$A227,monthly!$B:$B,"<="&$B227)) -> 235.34016 | AH227: =IF(COUNTIFS(monthly!Z:Z,"",monthly!$A:$A,">="&$A227,monthly!$B:$B,"<="&$B227)>0,"NA",AVERAGEIFS(monthly!Z:Z,monthly!$A:$A,">="&$A227,monthly!$B:$B,"<="&$B227)) -> 0.20705035

Sheet monthly
A1: month_start | B1: month_end | C1: ntwi | D1: aud_usd | E1: comm_price | F1: comm_price_bulk | G1: iron_ore | H1: coal | I1: brent_crude | J1: natural_gas | K1: cash_rate | L1: fed_funds | M1: au_us_policy_rate | N1: au_2yr_yield | O1: us_2yr_yield | P1: au_us_2yr | Q1: au_10yr_yield | R1: us_10yr_yield | S1: au_us_10yr | T1: vix | U1: gepu | V1: au_epu | W1: gpr_global | X1: gprt_global | Y1: gpra_global | Z1: gprc_au
A2: 25569 | B2: 25599 | D2: 1.1185 | G2: 9.8 | H2: 7.8 | I2: 1.2 | L2: 8.9767742 | Q2: 5.95 | R2: 7.7947619 | S2: =Q2-R2 -> -1.8447619
A3: 25600 | B3: 25627 | D3: 1.1209 | G3: 9.8 | H3: 7.8 | I3: 1.2 | L3: 8.9782143 | Q3: 5.96 | R3: 7.2383333 | S3: =Q3-R3 -> -1.2783333
A4: 25628 | B4: 25658 | D4: 1.1207 | G4: 9.8 | H4: 7.8 | I4: 1.2 | L4: 7.7622581 | Q4: 6.05 | R4: 7.0728571 | S4: =Q4-R4 -> -1.0228571
A5: 25659 | B5: 25688 | D5: 1.1206 | G5: 9.8 | H5: 7.8 | I5: 1.2 | L5: 8.0963333 | Q5: 6.94 | R5: 7.3909091 | S5: =Q5-R5 -> -0.45090909
A6: 25689 | B6: 25719 | C6: 100 | D6: 1.1186 | G6: 9.8 | H6: 7.8 | I6: 1.2 | L6: 7.9464516 | Q6: 6.85 | R6: 7.9061905 | S6: =Q6-R6 -> -1.0561905
A7: 25720 | B7: 25749 | C7: 99.6 | D7: 1.1159 | G7: 9.8 | H7: 7.8 | I7: 1.2 | L7: 7.605 | Q7: 6.86 | R7: 7.8418182 | S7: =Q7-R7 -> -0.98181818
A8: 25750 | B8: 25780 | C8: 99.4 | D8: 1.1134 | G8: 9.8 | H8: 7.8 | I8: 1.2 | L8: 7.2148387 | Q8: 6.89 | R8: 7.4572727 | S8: =Q8-R8 -> -0.56727273
A9: 25781 | B9: 25811 | C9: 99.1 | D9: 1.11 | G9: 9.8 | H9: 7.8 | I9: 1.2 | L9: 6.6151613 | Q9: 6.87 | R9: 7.5271429 | S9: =Q9-R9 -> -0.65714286
A10: 25812 | B10: 25841 | C10: 99.2 | D10: 1.1118 | G10: 9.8 | H10: 7.8 | I10: 1.2 | L10: 6.2896667 | Q10: 6.87 | R10: 7.3895238 | S10: =Q10-R10 -> -0.51952381
A11: 25842 | B11: 25872 | C11: 99.2 | D11: 1.1131 | G11: 9.8 | H11: 7.8 | I11: 1.2 | L11: 6.203871 | Q11: 6.88 | R11: 7.3266667 | S11: =Q11-R11 -> -0.44666667
A12: 25873 | B12: 25902 | C12: 99.2 | D12: 1.1131 | G12: 9.8 | H12: 7.8 | I12: 1.2 | L12: 5.6013333 | Q12: 6.83 | R12: 6.8411111 | S12: =Q12-R12 -> -0.011111111
A13: 25903 | B13: 25933 | C13: 99.3 | D13: 1.1146 | G13: 9.8 | H13: 7.8 | I13: 1.2 | L13: 4.9006452 | Q13: 6.81 | R13: 6.3913636 | S13: =Q13-R13 -> 0.41863636
A14: 25934 | B14: 25964 | C14: 100 | D14: 1.1257 | G14: 10.3 | H14: 8.7 | I14: 1.6 | L14: 4.1422581 | Q14: 6.85 | R14: 6.2385 | S14: =Q14-R14 -> 0.6115
A15: 25965 | B15: 25992 | C15: 100 | D15: 1.1262 | G15: 10.3 | H15: 8.7 | I15: 1.6 | L15: 3.7207143 | Q15: 6.85 | R15: 6.1122222 | S15: =Q15-R15 -> 0.73777778
A16: 25993 | B16: 26023 | C16: 100 | D16: 1.1257 | G16: 10.3 | H16: 8.7 | I16: 1.6 | L16: 3.7116129 | Q16: 6.84 | R16: 5.7034783 | S16: =Q16-R16 -> 1.1365217
A17: 26024 | B17: 26053 | C17: 100 | D17: 1.1267 | G17: 10.3 | H17: 8.7 | I17: 1.6 | L17: 4.156 | Q17: 6.85 | R17: 5.8338095 | S17: =Q17-R17 -> 1.0161905
... A73: 27729 | B73: 27759 | C73: 105.3 | D73: 1.2571 | G73: 17.3 | H73: 26.8 | I73: 10.5 | L73: 5.1954839 | Q73: 10 | R73: 7.9968182 | S73: =Q73-R73 -> 2.0031818
A74: 27760 | B74: 27790 | C74: 105.3 | D74: 1.2588 | G74: 22.7 | H74: 27.2 | I74: 11.5 | K74: 6.804 | L74: 4.8677419 | M74: =K74-L74 -> 1.9362581 | Q74: 10.02 | R74: 7.742381 | S74: =Q74-R74 -> 2.277619
A75: 27791 | B75: 27819 | C75: 105.3 | D75: 1.2607 | G75: 22.7 | H75: 27.2 | I75: 11.5 | K75: 7.166 | L75: 4.7706897 | M75: =K75-L75 -> 2.3953103 | Q75: 10 | R75: 7.7927778 | S75: =Q75-R75 -> 2.2072222
A76: 27820 | B76: 27850 | C76: 105.3 | D76: 1.2486 | G76: 22.7 | H76: 27.2 | I76: 11.5 | K76: 6.6973913 | L76: 4.8374194 | M76: =K76-L76 -> 1.8599719 | Q76: 9.99 | R76: 7.7343478 | S76: =Q76-R76 -> 2.2556522
A77: 27851 | B77: 27880 | C77: 105.3 | D77: 1.239 | G77: 22.7 | H77: 27.2 | I77: 11.5 | K77: 7.086 | L77: 4.816 | M77: =K77-L77 -> 2.27 | Q77: 10 | R77: 7.5642857 | S77: =Q77-R77 -> 2.4357143
A78: 27881 | B78: 27911 | C78: 105.3 | D78: 1.2271 | G78: 22.7 | H78: 27.2 | I78: 11.5 | K78: 7.7061905 | L78: 5.2906452 | M78: =K78-L78 -> 2.4155453 | Q78: 10 | R78: 7.895 | S78: =Q78-R78 -> 2.105
A79: 27912 | B79: 27941 | C79: 105.3 | D79: 1.2356 | G79: 22.7 | H79: 27.2 | I79: 11.5 | K79: 8.0227273 | L79: 5.4763333 | M79: =K79-L79 -> 2.5463939 | O79: 7.06 | Q79: 9.99 | R79: 7.8613636 | S79: =Q79-R79 -> 2.1286364
A80: 27942 | B80: 27972 | C80: 105.3 | D80: 1.2407 | G80: 22.7 | H80: 27.2 | I80: 11.6 | K80: 7.5713636 | L80: 5.3064516 | M80: =K80-L80 -> 2.264912 | O80: 6.85 | Q80: 10 | R80: 7.8319048 | S80: =Q80-R80 -> 2.1680952
A81: 27973 | B81: 28003 | C81: 105.3 | D81: 1.2462 | G81: 22.7 | H81: 27.2 | I81: 11.6 | K81: 7.7490909 | L81: 5.2909677 | M81: =K81-L81 -> 2.4581232 | O81: 6.6313636 | Q81: 9.99 | R81: 7.7686364 | S81: =Q81-R81 -> 2.2213636
A82: 28004 | B82: 28033 | C82: 105.3 | D82: 1.2373 | G82: 22.7 | H82: 27.2 | I82: 11.6 | K82: 7.4622727 | L82: 5.252 | M82: =K82-L82 -> 2.2102727 | O82: 6.4161905 | Q82: 9.99 | R82: 7.5942857 | S82: =Q82-R82 -> 2.3957143
A83: 28034 | B83: 28064 | C83: 105.3 | D83: 1.2261 | G83: 22.7 | H83: 27.2 | I83: 11.9 | K83: 7.2771429 | L83: 5.0248387 | M83: =K83-L83 -> 2.2523041 | O83: 5.984 | Q83: 9.98 | R83: 7.411 | S83: =Q83-R83 -> 2.569
A84: 28065 | B84: 28094 | C84: 86.9 | D84: 1.0123 | G84: 22.7 | H84: 27.2 | I84: 11.9 | K84: 7.1754545 | L84: 4.949 | M84: =K84-L84 -> 2.2264545 | O84: 5.81 | Q84: 10 | R84: 7.2910526 | S84: =Q84-R84 -> 2.7089474
A85: 28095 | B85: 28125 | C85: 92.2 | D85: 1.0864 | G85: 22.7 | H85: 27.2 | I85: 11.9 | K85: 6.3719048 | L85: 4.6512903 | M85: =K85-L85 -> 1.7206144 | O85: 5.3768182 | Q85: 10.41 | R85: 6.8690909 | S85: =Q85-R85 -> 3.5409091
A86: 28126 | B86: 28156 | C86: 92.2 | D86: 1.087 | G86: 23.1 | H86: 28.7 | I86: 12.5 | J86: 2.77 | K86: 7.4563158 | L86: 4.6109677 | M86: =K86-L86 -> 2.845348 | O86: 5.8995238 | Q86: 10.4 | R86: 7.2133333 | S86: =Q86-R86 -> 3.1866667
A87: 28157 | B87: 28184 | C87: 92.5 | D87: 1.0967 | G87: 23.1 | H87: 28.7 | I87: 12.5 | J87: 2.77 | K87: 7.4235 | L87: 4.6832143 | M87: =K87-L87 -> 2.7402857 | O87: 6.0884211 | Q87: 10.4 | R87: 7.3910526 | S87: =Q87-R87 -> 3.0089474
A88: 28185 | B88: 28215 | C88: 92.5 | D88: 1.1031 | G88: 23.1 | H88: 28.7 | I88: 12.5 | J88: 2.77 | K88: 7.5756522 | L88: 4.69 | M88: =K88-L88 -> 2.8856522 | O88: 6.0865217 | Q88: 10.4 | R88: 7.46 | S88: =Q88-R88 -> 2.94
A89: 28216 | B89: 28245 | C89: 92.5 | D89: 1.1045 | G89: 23.1 | H89: 28.7 | I89: 12.4 | J89: 2.77 | K89: 7.3622222 | L89: 4.7273333 | M89: =K89-L89 -> 2.6348889 | O89: 5.9635 | Q89: 10.4 | R89: 7.3705 | S89: =Q89-R89 -> 3.0295
A90: 28246 | B90: 28276 | C90: 92.5 | D90: 1.1039 | G90: 23.1 | H90: 28.7 | I90: 12.4 | J90: 2.77 | K90: 8.6440909 | L90: 5.35 | M90: =K90-L90 -> 3.2940909 | O90: 6.2547619 | Q90: 10.41 | R90: 7.4566667 | S90: =Q90-R90 -> 2.9533333
A91: 28277 | B91: 28306 | C91: 92.5 | D91: 1.1155 | G91: 23.1 | H91: 28.7 | I91: 12.4 | J91: 2.77 | K91: 9.5204545 | L91: 5.3886667 | M91: =K91-L91 -> 4.1317879 | O91: 6.1272727 | Q91: 10.41 | R91: 7.2754545 | S91: =Q91-R91 -> 3.1345455
A92: 28307 | B92: 28337 | C92: 92.5 | D92: 1.1225 | G92: 23.1 | H92: 28.7 | I92: 12.6 | J92: 2.77 | K92: 9.3361905 | L92: 5.4193548 | M92: =K92-L92 -> 3.9168356 | O92: 6.2747368 | Q92: 10.41 | R92: 7.33 | S92: =Q92-R92 -> 3.08
A93: 28338 | B93: 28368 | C93: 91.5 | D93: 1.1051 | G93: 23.1 | H93: 28.7 | I93: 12.6 | J93: 2.77 | K93: 9.6695652 | L93: 5.9019355 | M93: =K93-L93 -> 3.7676297 | O93: 6.6113043 | Q93: 10.41 | R93: 7.3965217 | S93: =Q93-R93 -> 3.0134783
A94: 28369 | B94: 28398 | C94: 91.5 | D94: 1.1076 | G94: 23.1 | H94: 28.7 | I94: 12.6 | J94: 2.77 | K94: 9.4690909 | L94: 6.1383333 | M94: =K94-L94 -> 3.3307576 | O94: 6.7142857 | Q94: 10.18 | R94: 7.3438095 | S94: =Q94-R94 -> 2.8361905
A95: 28399 | B95: 28429 | C95: 90.9 | D95: 1.1236 | G95: 23.1 | H95: 28.7 | I95: 12.7 | J95: 2.77 | K95: 8.8547619 | L95: 6.4654839 | M95: =K95-L95 -> 2.389278 | O95: 7.106 | Q95: 10.01 | R95: 7.5235 | S95: =Q95-R95 -> 2.4865
A96: 28430 | B96: 28459 | C96: 90 | D96: 1.1274 | G96: 23.1 | H96: 28.7 | I96: 12.7 | J96: 2.77 | K96: 9.1636364 | L96: 6.5076667 | M96: =K96-L96 -> 2.6559697 | O96: 7.1426316 | Q96: 9.79 | R96: 7.5773684 | S96: =Q96-R96 -> 2.2126316
A97: 28460 | B97: 28490 | C97: 89.4 | D97: 1.1414 | G97: 23.1 | H97: 28.7 | I97: 12.7 | J97: 2.77 | K97: 9.1480952 | L97: 6.5606452 | M97: =K97-L97 -> 2.5874501 | O97: 7.1766667 | Q97: 9.5 | R97: 7.6852381 | S97: =Q97-R97 -> 1.8147619
... A151: 30103 | B151: 30132 | C151: 88.2 | D151: 1.0223 | G151: 32.5 | H151: 55.6 | I151: 34.6 | J151: 6.05 | K151: 14.84 | L151: 14.152667 | M151: =K151-L151 -> 0.68733333 | O151: 14.465455 | Q151: 16.4 | R151: 14.299545 | S151: =Q151-R151 -> 2.1004545
A152: 30133 | B152: 30163 | C152: 86.1 | D152: 0.9958 | E152: 41.46928 | G152: 32.5 | H152: 55.6 | I152: 33.7 | J152: 6.05 | K152: 13.74 | L152: 12.586774 | M152: =K152-L152 -> 1.1532258 | O152: 13.797143 | Q152: 16.4 | R152: 13.94619 | S152: =Q152-R152 -> 2.4538095
A153: 30164 | B153: 30194 | C153: 84.1 | D153: 0.9643 | E153: 41.324053 | G153: 32.5 | H153: 55.6 | I153: 32.8 | J153: 6.05 | K153: 14.950909 | L153: 10.119032 | M153: =K153-L153 -> 4.8318768 | O153: 12.323636 | Q153: 16.5 | R153: 13.055 | S153: =Q153-R153 -> 3.445
A154: 30195 | B154: 30224 | C154: 83.8 | D154: 0.9493 | E154: 42.244801 | G154: 32.5 | H154: 55.6 | I154: 34.3 | J154: 6.05 | K154: 14.022273 | L154: 10.309667 | M154: =K154-L154 -> 3.7126061 | O154: 11.783333 | Q154: 15.2 | R154: 12.339048 | S154: =Q154-R154 -> 2.8609524
A155: 30225 | B155: 30255 | C155: 83.9 | D155: 0.9367 | E155: 42.372496 | G155: 32.5 | H155: 55.6 | I155: 35 | J155: 6.05 | K155: 13.372381 | L155: 9.7070968 | M155: =K155-L155 -> 3.6652842 | O155: 10.1875 | Q155: 14.55 | R155: 10.9065 | S155: =Q155-R155 -> 3.6435
A156: 30256 | B156: 30285 | C156: 83.5 | D156: 0.9548 | E156: 42.566438 | G156: 32.5 | H156: 55.6 | I156: 33.8 | J156: 6.05 | K156: 12.305 | L156: 9.1963333 | M156: =K156-L156 -> 3.1086667 | O156: 9.7957895 | Q156: 14.6 | R156: 10.550526 | S156: =Q156-R156 -> 4.0494737
A157: 30286 | B157: 30316 | C157: 83.4 | D157: 0.9806 | E157: 41.907159 | G157: 32.5 | H157: 45.5 | I157: 31.8 | J157: 6.05 | K157: 10.194762 | L157: 8.9454839 | M157: =K157-L157 -> 1.249278 | O157: 9.6622727 | Q157: 14 | R157: 10.54 | S157: =Q157-R157 -> 3.46
A158: 30317 | B158: 30347 | C158: 83.6 | D158: 0.9718 | E158: 42.558159 | G158: 29 | H158: 43 | I158: 30.9 | J158: 5.55 | K158: 10.070526 | L158: 8.6832258 | M158: =K158-L158 -> 1.3873005 | O158: 9.327619 | Q158: 13 | R158: 10.457143 | S158: =Q158-R158 -> 2.5428571
A159: 30348 | B159: 30375 | C159: 82.4 | D159: 0.9606 | E159: 43.361853 | G159: 29 | H159: 43 | I159: 29.1 | J159: 5.55 | K159: 11.171 | L159: 8.5089286 | M159: =K159-L159 -> 2.6620714 | O159: 9.6363158 | Q159: 13.6 | R159: 10.724737 | S159: =Q159-R159 -> 2.8752632
A160: 30376 | B160: 30406 | C160: 76.1 | D160: 0.8629 | E160: 41.968984 | G160: 29 | H160: 43 | I160: 28.2 | J160: 5.55 | K160: 10.520435 | L160: 8.766129 | M160: =K160-L160 -> 1.7543058 | O160: 9.656087 | Q160: 14.4 | R160: 10.506522 | S160: =Q160-R160 -> 3.8934783
A161: 30407 | B161: 30436 | C161: 76.2 | D161: 0.868 | E161: 42.133724 | G161: 29 | H161: 43 | I161: 29.8 | J161: 5.55 | K161: 11.761111 | L161: 8.802 | M161: =K161-L161 -> 2.9591111 | O161: 9.568 | Q161: 14.1 | R161: 10.4 | S161: =Q161-R161 -> 3.7
A162: 30437 | B162: 30467 | C162: 77.6 | D162: 0.882 | E162: 42.60052 | G162: 29 | H162: 43 | I162: 29.6 | J162: 5.55 | K162: 10.813182 | L162: 8.63 | M162: =K162-L162 -> 2.1831818 | O162: 9.4890476 | Q162: 13.1 | R162: 10.38 | S162: =Q162-R162 -> 2.72
A163: 30468 | B163: 30497 | C163: 77.7 | D163: 0.8745 | E163: 42.806771 | G163: 29 | H163: 43 | I163: 30.2 | J163: 5.55 | K163: 9.995 | L163: 8.982 | M163: =K163-L163 -> 1.013 | O163: 10.181818 | Q163: 14.7 | R163: 10.848636 | S163: =Q163-R163 -> 3.8513636
... A181: 31017 | B181: 31047 | C181: 81.3 | D181: 0.8278 | E181: 40.216866 | G181: 26.2 | H181: 33.8 | I181: 27 | J181: 5.24 | K181: 10.996667 | L181: 8.3816129 | M181: =K181-L181 -> 2.6150538 | O181: 10.1815 | Q181: 13.4 | R181: 11.4995 | S181: =Q181-R181 -> 1.9005
A182: 31048 | B182: 31078 | C182: 80.8 | D182: 0.815 | E182: 40.530259 | G182: 26.6 | H182: 33.8 | I182: 27 | J182: 5.23 | K182: 10.846667 | L182: 8.3490323 | M182: =K182-L182 -> 2.4976344 | O182: 9.9309524 | Q182: 13.1 | R182: 11.384286 | S182: =Q182-R182 -> 1.7157143 | W182: 102.17338 | X182: 107.57417 | Y182: 89.647491 | Z182: 0.060428176
A183: 31079 | B183: 31106 | C183: 72.3 | D183: 0.7138 | E183: 40.29067 | G183: 26.6 | H183: 33.8 | I183: 28.2 | J183: 5.23 | K183: 11.2145 | L183: 8.5014286 | M183: =K183-L183 -> 2.7130714 | O183: 10.165556 | Q183: 13.7 | R183: 11.508889 | S183: =Q183-R183 -> 2.1911111 | W183: 117.10202 | X183: 126.44273 | Y183: 96.601669 | Z183: 0.35123393
A184: 31107 | B184: 31137 | C184: 69.2 | D184: 0.7051 | E184: 40.227765 | G184: 26.6 | H184: 33.8 | I184: 28.1 | J184: 5.23 | K184: 13.487143 | L184: 8.5774194 | M184: =K184-L184 -> 4.9097235 | O184: 10.712857 | Q184: 13.8 | R184: 11.855238 | S184: =Q184-R184 -> 1.9447619 | W184: 124.77815 | X184: 127.07085 | Y184: 116.98727 | Z184: 0.12204052
A185: 31138 | B185: 31167 | C185: 64.2 | D185: 0.6523 | E185: 38.663264 | G185: 26.6 | H185: 33.8 | I185: 27.9 | J185: 5.23 | K185: 14.624211 | L185: 8.2673333 | M185: =K185-L185 -> 6.3568772 | O185: 10.089048 | Q185: 13.95 | R185: 11.434762 | S185: =Q185-R185 -> 2.5152381 | W185: 87.929001 | X185: 94.640198 | Y185: 73.757797 | Z185: 0.070224717
A186: 31168 | B186: 31198 | C186: 64.8 | D186: 0.658 | E186: 38.797639 | G186: 26.6 | H186: 33.8 | I186: 26.7 | J186: 5.23 | K186: 14.983478 | L186: 7.9709677 | M186: =K186-L186 -> 7.0125105 | O186: 9.3940909 | Q186: 13.8 | R186: 10.846818 | S186: =Q186-R186 -> 2.9531818 | W186: 103.26285 | X186: 111.15978 | Y186: 92.276726 | Z186: 0.043318171
A187: 31199 | B187: 31228 | C187: 65 | D187: 0.6655 | E187: 37.611797 | G187: 26.6 | H187: 33.8 | I187: 26.5 | J187: 5.23 | K187: 15.1705 | L187: 7.5333333 | M187: =K187-L187 -> 7.6371667 | O187: 8.688 | Q187: 13.5 | R187: 10.156 | S187: =Q187-R187 -> 3.344 | W187: 148.78282 | X187: 134.65671 | Y187: 174.14375 | Z187: 0.030776333
A188: 31229 | B188: 31259 | C188: 68.5 | D188: 0.7271 | E188: 37.116266 | G188: 26.6 | H188: 33.8 | I188: 26.6 | J188: 5.23 | K188: 14.792609 | L188: 7.883871 | M188: =K188-L188 -> 6.9087377 | O188: 8.7731818 | Q188: 13.4 | R188: 10.306818 | S188: =Q188-R188 -> 3.0931818 | W188: 133.90543 | X188: 126.30108 | Y188: 149.54236 | Z188: 0.15316541
A189: 31260 | B189: 31290 | C189: 66.4 | D189: 0.7034 | E189: 36.519982 | G189: 26.6 | H189: 33.8 | I189: 27.2 | J189: 5.23 | K189: 15.465909 | L189: 7.8983871 | M189: =K189-L189 -> 7.567522 | O189: 8.9436364 | Q189: 13.95 | R189: 10.331818 | S189: =Q189-R189 -> 3.6181818 | W189: 82.784103 | X189: 75.26384 | Y189: 84.879532 | Z189: 0.12582837
A190: 31291 | B190: 31320 | C190: 64.8 | D190: 0.7077 | E190: 36.73235 | G190: 26.6 | H190: 33.8 | I190: 27.2 | J190: 5.23 | K190: 15.984286 | L190: 7.9213333 | M190: =K190-L190 -> 8.0629524 | O190: 8.9831579 | Q190: 13.8 | R190: 10.373158 | S190: =Q190-R190 -> 3.4268421 | W190: 102.43449 | X190: 101.5695 | Y190: 92.486313 | Z190: 0.14290251
A191: 31321 | B191: 31351 | C191: 63.4 | D191: 0.7002 | E191: 35.586491 | G191: 26.6 | H191: 33.8 | I191: 27.9 | J191: 5.23 | K191: 15.841739 | L191: 7.9864516 | M191: =K191-L191 -> 7.8552875 | O191: 8.8645455 | Q191: 14.55 | R191: 10.236818 | S191: =Q191-R191 -> 4.3131818 | W191: 105.99191 | X191: 91.342209 | Y191: 118.73129 | Z191: 0.13432837
A192: 31352 | B192: 31381 | C192: 60.9 | D192: 0.685 | E192: 35.253308 | G192: 26.6 | H192: 33.8 | I192: 29.1 | J192: 5.23 | K192: 17.401429 | L192: 8.0506667 | M192: =K192-L192 -> 9.3507619 | O192: 8.5810526 | Q192: 15.05 | R192: 9.7815789 | S192: =Q192-R192 -> 5.2684211 | W192: 94.848183 | X192: 98.258377 | Y192: 80.122139 | Z192: 0.039077766
A193: 31382 | B193: 31412 | C193: 60.7 | D193: 0.6809 | E193: 35.074406 | G193: 26.6 | H193: 33.8 | I193: 25.9 | J193: 5.23 | K193: 18.3765 | L193: 8.2745161 | M193: =K193-L193 -> 10.101984 | O193: 8.1466667 | Q193: 14.85 | R193: 9.2590476 | S193: =Q193-R193 -> 5.5909524 | W193: 96.421165 | X193: 80.304565 | Y193: 111.21063 | Z193: 0.055161543
... A241: 32843 | B241: 32873 | C241: 61.1 | D241: 0.7927 | E241: 38.971884 | G241: 27.8 | H241: 38 | I241: 19.9 | J241: 3.28 | K241: 17.898947 | L241: 8.4525806 | M241: =K241-L241 -> 9.4463667 | O241: 7.777 | Q241: 12.9 | R241: 7.836 | S241: =Q241-R241 -> 5.064 | W241: 112.55353 | X241: 101.52502 | Y241: 128.65443 | Z241: 0.095388189
A242: 32874 | B242: 32904 | C242: 59.4 | D242: 0.7708 | E242: 38.239842 | G242: 32.5 | H242: 38 | I242: 21 | J242: 3.64 | K242: 17.704091 | L242: 8.2290323 | M242: =K242-L242 -> 9.4750587 | O242: 8.0852381 | Q242: 12.8 | R242: 8.2066667 | S242: =Q242-R242 -> 4.5933333 | T242: 23.347273 | W242: 81.544044 | X242: 76.011421 | Y242: 80.726074 | Z242: 0.057355892
A243: 32905 | B243: 32932 | C243: 59 | D243: 0.7594 | E243: 37.274124 | G243: 32.5 | H243: 38 | I243: 19.9 | J243: 3.64 | K243: 16.691 | L243: 8.2371429 | M243: =K243-L243 -> 8.4538571 | O243: 8.3705263 | Q243: 13.3 | R243: 8.4731579 | S243: =Q243-R243 -> 4.8268421 | T243: 23.262632 | W243: 77.407211 | X243: 81.10881 | Y243: 65.389038 | Z243: 0.040183954
A244: 32933 | B244: 32963 | C244: 59.8 | D244: 0.7542 | E244: 38.222347 | G244: 32.5 | H244: 38 | I244: 18.5 | J244: 3.64 | K244: 16.316818 | L244: 8.2767742 | M244: =K244-L244 -> 8.040044 | O244: 8.6268182 | Q244: 13.44 | R244: 8.5886364 | S244: =Q244-R244 -> 4.8513636 | T244: 20.062273 | W244: 67.591942 | X244: 68.186722 | Y244: 59.722858 | Z244: 0.019418985
A245: 32964 | B245: 32993 | C245: 59.6 | D245: 0.7509 | E245: 38.469194 | G245: 32.5 | H245: 38 | I245: 16.8 | J245: 3.64 | K245: 15.096111 | L245: 8.255 | M245: =K245-L245 -> 6.8411111 | O245: 8.724 | Q245: 13.78 | R245: 8.7855 | S245: =Q245-R245 -> 4.9945 | T245: 21.4035 | W245: 81.643845 | X245: 97.976547 | Y245: 54.792671 | Z245: 0.016380016
A246: 32994 | B246: 33024 | C246: 60.2 | D246: 0.7691 | E246: 37.778774 | G246: 32.5 | H246: 40.5 | I246: 16.7 | J246: 3.64 | K246: 14.962174 | L246: 8.1764516 | M246: =K246-L246 -> 6.7857223 | O246: 8.6422727 | Q246: 13.51 | R246: 8.7581818 | S246: =Q246-R246 -> 4.7518182 | T246: 18.097727 | W246: 86.40712 | X246: 97.816574 | Y246: 66.843781 | Z246: 0.015875535
A247: 33025 | B247: 33054 | C247: 61.6 | D247: 0.789 | E247: 36.708229 | G247: 32.5 | H247: 40.5 | I247: 15.7 | J247: 3.64 | K247: 14.977 | L247: 8.2886667 | M247: =K247-L247 -> 6.6883333 | O247: 8.3509524 | Q247: 13.4 | R247: 8.48 | S247: =Q247-R247 -> 4.92 | T247: 16.822381 | W247: 79.681107 | X247: 72.84642 | Y247: 80.652878 | Z247: 0.045641258
A248: 33055 | B248: 33085 | C248: 60.4 | D248: 0.7901 | E248: 35.678058 | G248: 32.5 | H248: 40.5 | I248: 17.6 | J248: 3.64 | K248: 14.947273 | L248: 8.1525806 | M248: =K248-L248 -> 6.7946921 | O248: 8.1571429 | Q248: 13.16 | R248: 8.4714286 | S248: =Q248-R248 -> 4.6885714 | T248: 18.392857 | W248: 85.78743 | X248: 82.369255 | Y248: 81.847137 | Z248: 0.033800911
A249: 33086 | B249: 33116 | C249: 61.4 | D249: 0.8162 | E249: 36.099166 | G249: 32.5 | H249: 40.5 | I249: 27.1 | J249: 3.64 | K249: 14 | L249: 8.1341935 | M249: =K249-L249 -> 5.8658065 | O249: 8.0613043 | Q249: 13.49 | R249: 8.7526087 | S249: =Q249-R249 -> 4.7373913 | T249: 28.175217 | W249: 250.45108 | X249: 353.76312 | Y249: 128.2502 | Z249: 0.24392261
A250: 33117 | B250: 33146 | C250: 61.6 | D250: 0.8265 | E250: 36.676073 | G250: 32.5 | H250: 40.5 | I250: 34.1 | J250: 3.64 | K250: 14 | L250: 8.195 | M250: =K250-L250 -> 5.805 | O250: 8.0794737 | Q250: 13.63 | R250: 8.8931579 | S250: =Q250-R250 -> 4.7368421 | T250: 29.107368 | W250: 188.66054 | X250: 262.12363 | Y250: 106.95481 | Z250: 0.14945821
A251: 33147 | B251: 33177 | C251: 57.2 | D251: 0.7847 | E251: 35.161289 | G251: 32.5 | H251: 40.5 | I251: 36.1 | J251: 3.64 | K251: 13.434783 | L251: 8.1125806 | M251: =K251-L251 -> 5.322202 | O251: 7.8777273 | Q251: 13.35 | R251: 8.7195455 | S251: =Q251-R251 -> 4.6304545 | T251: 29.625652 | W251: 143.85257 | X251: 172.94637 | Y251: 105.10759 | Z251: 0.15242115
A252: 33178 | B252: 33207 | C252: 56.9 | D252: 0.7745 | E252: 33.544563 | G252: 32.5 | H252: 40.5 | I252: 33 | J252: 3.64 | K252: 13 | L252: 7.8066667 | M252: =K252-L252 -> 5.1933333 | O252: 7.5995 | Q252: 12.23 | R252: 8.392 | S252: =Q252-R252 -> 3.838 | T252: 24.885714 | W252: 158.74355 | X252: 201.18106 | Y252: 115.40346 | Z252: 0.1007902
A253: 33208 | B253: 33238 | C253: 57.3 | D253: 0.7733 | E253: 33.184666 | G253: 32.5 | H253: 40.5 | I253: 28 | J253: 3.64 | K253: 12.578947 | L253: 7.3129032 | M253: =K253-L253 -> 5.2660441 | O253: 7.314 | Q253: 12.07 | R253: 8.075 | S253: =Q253-R253 -> 3.995 | T253: 23.363 | W253: 153.16243 | X253: 194.64853 | Y253: 103.18326 | Z253: 0.12089288
... A301: 34669 | B301: 34699 | C301: 56.2 | D301: 0.7768 | E301: 31.640938 | G301: 26.5 | H301: 36.1 | I301: 16 | J301: 3.29 | K301: 7.05 | L301: 5.4532258 | M301: =K301-L301 -> 1.5967742 | O301: 7.5895238 | Q301: 10.04 | R301: 7.8138095 | S301: =Q301-R301 -> 2.2261905 | T301: 14.177143 | W301: 96.047501 | X301: 107.74174 | Y301: 81.616096 | Z301: 0.014173842
A302: 34700 | B302: 34730 | C302: 54.5 | D302: 0.7583 | E302: 32.000502 | G302: 28.4 | H302: 37.1 | I302: 16.6 | J302: 3.36 | K302: 7.5 | L302: 5.5274194 | M302: =K302-L302 -> 1.9725806 | N302: 10.202 | O302: 7.507 | P302: =N302-O302 -> 2.695 | Q302: 10.3345 | R302: 7.7795 | S302: =Q302-R302 -> 2.555 | T302: 12.274286 | W302: 80.154678 | X302: 84.899139 | Y302: 70.477058 | Z302: 0.044112783
A303: 34731 | B303: 34758 | C303: 52.9 | D303: 0.7395 | E303: 31.056984 | G303: 28.4 | H303: 37.6 | I303: 17.1 | J303: 3.4 | K303: 7.5 | L303: 5.9153571 | M303: =K303-L303 -> 1.5846429 | N303: 9.5605 | O303: 7.1115789 | P303: =N303-O303 -> 2.4489211 | Q303: 10.1465 | R303: 7.4694737 | S303: =Q303-R303 -> 2.6770263 | T303: 11.47 | W303: 76.875328 | X303: 72.59407 | Y303: 77.145996 | Z303: 0.027973145
A304: 34759 | B304: 34789 | C304: 50.7 | D304: 0.728 | E304: 29.824455 | G304: 28.4 | H304: 38.4 | I304: 17 | J304: 3.46 | K304: 7.5 | L304: 5.9764516 | M304: =K304-L304 -> 1.5235484 | N304: 9.37 | O304: 6.7756522 | P304: =N304-O304 -> 2.5943478 | Q304: 10.137826 | R304: 7.2047826 | S304: =Q304-R304 -> 2.9330435 | T304: 12.166522 | W304: 82.244446 | X304: 79.159042 | Y304: 79.87529 | Z304: 0.028232638
A305: 34790 | B305: 34819 | C305: 49.6 | D305: 0.7299 | E305: 29.274249 | G305: 28.4 | H305: 37.1 | I305: 18.7 | J305: 3.45 | K305: 7.5 | L305: 6.0473333 | M305: =K305-L305 -> 1.4526667 | N305: 8.8952941 | O305: 6.5678947 | P305: =N305-O305 -> 2.3273994 | Q305: 9.7988235 | R305: 7.0626316 | S305: =Q305-R305 -> 2.736192 | T305: 12.442632 | W305: 99.19088 | X305: 93.923035 | Y305: 99.147942 | Z305: 0.040552996
A306: 34820 | B306: 34850 | C306: 48.5 | D306: 0.7138 | E306: 29.691276 | G306: 28.4 | H306: 38.8 | I306: 18.4 | J306: 3.53 | K306: 7.5 | L306: 6.0090323 | M306: =K306-L306 -> 1.4909677 | N306: 8.1904348 | O306: 6.1709091 | P306: =N306-O306 -> 2.0195257 | Q306: 9.106087 | R306: 6.6327273 | S306: =Q306-R306 -> 2.4733597 | T306: 12.265909 | W306: 87.842529 | X306: 96.409195 | Y306: 79.349617 | Z306: 0.054511756
A307: 34851 | B307: 34880 | C307: 48.4 | D307: 0.7086 | E307: 29.921605 | G307: 28.4 | H307: 40.8 | I307: 17.4 | J307: 3.56 | K307: 7.5 | L307: 6.0013333 | M307: =K307-L307 -> 1.4986667 | N307: 7.6580952 | O307: 5.7159091 | P307: =N307-O307 -> 1.9421861 | Q307: 8.8561905 | R307: 6.1681818 | S307: =Q307-R307 -> 2.6880087 | T307: 11.896818 | W307: 104.60776 | X307: 121.57905 | Y307: 85.120949 | Z307: 0.066521302
A308: 34881 | B308: 34911 | C308: 51 | D308: 0.7389 | E308: 29.996797 | G308: 28.4 | H308: 41.1 | I308: 15.9 | J308: 3.48 | K308: 7.5 | L308: 5.8519355 | M308: =K308-L308 -> 1.6480645 | N308: 7.6861905 | O308: 5.78 | P308: =N308-O308 -> 1.9061905 | Q308: 9.0819048 | R308: 6.278 | S308: =Q308-R308 -> 2.8039048 | T308: 12.514 | W308: 107.64542 | X308: 115.32477 | Y308: 100.19745 | Z308: 0.081887305
A309: 34912 | B309: 34942 | C309: 53.9 | D309: 0.7524 | E309: 30.92876 | G309: 28.4 | H309: 40.9 | I309: 16.1 | J309: 3.46 | K309: 7.5 | L309: 5.7351613 | M309: =K309-L309 -> 1.7648387 | N309: 7.9308696 | O309: 5.9808696 | P309: =N309-O309 -> 1.95 | Q309: 9.1243478 | R309: 6.4882609 | S309: =Q309-R309 -> 2.636087 | T309: 12.798261 | W309: 106.93478 | X309: 118.49734 | Y309: 100.76746 | Z309: 0.12125479
A310: 34943 | B310: 34972 | C310: 53.8 | D310: 0.755 | E310: 31.586551 | G310: 28.4 | H310: 40.9 | I310: 16.8 | J310: 3.46 | K310: 7.5 | L310: 5.8046667 | M310: =K310-L310 -> 1.6953333 | N310: 7.5914286 | O310: 5.806 | P310: =N310-O310 -> 1.7854286 | Q310: 8.6861905 | R310: 6.1975 | S310: =Q310-R310 -> 2.4886905 | T310: 12.057 | W310: 71.20517 | X310: 72.984016 | Y310: 68.817551 | Z310: 0.090881549
A311: 34973 | B311: 35003 | C311: 54.3 | D311: 0.7566 | E311: 30.756766 | G311: 28.4 | H311: 41 | I311: 16.1 | J311: 3.45 | K311: 7.5 | L311: 5.756129 | M311: =K311-L311 -> 1.743871 | N311: 7.5409091 | O311: 5.6971429 | P311: =N311-O311 -> 1.8437662 | Q311: 8.5086364 | R311: 6.0447619 | S311: =Q311-R311 -> 2.4638745 | T311: 14.357273 | W311: 67.741501 | X311: 64.277809 | Y311: 69.12648 | Z311: 0.04822376
A312: 35004 | B312: 35033 | C312: 53.8 | D312: 0.7469 | E312: 31.185997 | G312: 28.4 | H312: 39.6 | I312: 16.9 | J312: 3.41 | K312: 7.5 | L312: 5.803 | M312: =K312-L312 -> 1.697 | N312: 7.5427273 | O312: 5.4785714 | P312: =N312-O312 -> 2.0641558 | Q312: 8.495 | R312: 5.9304762 | S312: =Q312-R312 -> 2.5645238 | T312: 12.469048 | W312: 76.333496 | X312: 78.812622 | Y312: 69.865883 | Z312: 0.059759468
A313: 35034 | B313: 35064 | C313: 53.9 | D313: 0.745 | E313: 31.301572 | G313: 28.4 | H313: 39.4 | I313: 18 | J313: 3.37 | K313: 7.5 | L313: 5.6019355 | M313: =K313-L313 -> 1.8980645 | N313: 7.4094737 | O313: 5.3245 | P313: =N313-O313 -> 2.0849737 | Q313: 8.2547368 | R313: 5.7115 | S313: =Q313-R313 -> 2.5432368 | T313: 11.7485 | W313: 65.672058 | X313: 68.982018 | Y313: 55.3638 | Z313: 0.01591723
... A325: 35400 | B325: 35430 | C325: 59.4 | D325: 0.7965 | E325: 31.828767 | G325: 30 | H325: 35.4 | I325: 23.9 | J325: 4.08 | K325: 6.175 | L325: 5.2945161 | M325: =K325-L325 -> 0.88048387 | N325: 6.3675 | O325: 5.7819048 | P325: =N325-O325 -> 0.58559524 | Q325: 7.324 | R325: 6.302381 | S325: =Q325-R325 -> 1.021619 | T325: 19.260952 | W325: 74.982635 | X325: 80.178627 | Y325: 66.176483 | Z325: 0.03779861
A326: 35431 | B326: 35461 | C326: 58.1 | D326: 0.762 | E326: 32.345639 | G326: 30.2 | H326: 35.2 | I326: 23.5 | J326: 4.13 | K326: 6 | L326: 5.2545161 | M326: =K326-L326 -> 0.74548387 | N326: 6.232381 | O326: 6.0080952 | P326: =N326-O326 -> 0.22428571 | Q326: 7.4590476 | R326: 6.5790476 | S326: =Q326-R326 -> 0.88 | T326: 19.473333 | U326: 77.592551 | W326: 54.062435 | X326: 53.257828 | Y326: 55.227325 | Z326: 0.030168187
A327: 35462 | B327: 35489 | C327: 59.3 | D327: 0.7758 | E327: 33.085052 | G327: 30.2 | H327: 34.6 | I327: 20.8 | J327: 4.22 | K327: 6 | L327: 5.1857143 | M327: =K327-L327 -> 0.81428571 | N327: 6.3295 | O327: 5.8984211 | P327: =N327-O327 -> 0.43107895 | Q327: 7.394 | R327: 6.4194737 | S327: =Q327-R327 -> 0.97452632 | T327: 20.139474 | U327: 77.921979 | W327: 50.55994 | X327: 54.501366 | Y327: 43.509159 | Z327: 0.022031285
A328: 35490 | B328: 35520 | C328: 60.5 | D328: 0.7865 | E328: 33.857101 | G328: 30.2 | H328: 34.5 | I328: 19.2 | J328: 4.25 | K328: 6 | L328: 5.386129 | M328: =K328-L328 -> 0.61387097 | N328: 6.7326316 | O328: 6.222 | P328: =N328-O328 -> 0.51063158 | Q328: 7.8994737 | R328: 6.6945 | S328: =Q328-R328 -> 1.2049737 | T328: 20.17 | U328: 68.79603 | W328: 58.480061 | X328: 56.366299 | Y328: 59.907318 | Z328: 0.049086981
A329: 35521 | B329: 35550 | C329: 60.7 | D329: 0.7811 | E329: 33.609979 | G329: 30.2 | H329: 35.4 | I329: 17.5 | J329: 4.07 | K329: 6 | L329: 5.5073333 | M329: =K329-L329 -> 0.49266667 | N329: 6.5385714 | O329: 6.4481818 | P329: =N329-O329 -> 0.09038961 | Q329: 7.9238095 | R329: 6.8854545 | S329: =Q329-R329 -> 1.038355 | T329: 19.662273 | U329: 73.754836 | W329: 62.844486 | X329: 62.376057 | Y329: 61.280483 | Z329: 0.053951982
A330: 35551 | B330: 35581 | C330: 58 | D330: 0.7613 | E330: 33.446387 | G330: 30.2 | H330: 35.7 | I330: 19.1 | J330: 4.03 | K330: 5.8636364 | L330: 5.5041935 | M330: =K330-L330 -> 0.35944282 | N330: 6.3 | O330: 6.2766667 | P330: =N330-O330 -> 0.023333333 | Q330: 7.6745455 | R330: 6.7109524 | S330: =Q330-R330 -> 0.96359307 | T330: 19.924762 | U330: 77.328389 | W330: 53.576015 | X330: 53.544285 | Y330: 49.572899 | Z330: 0.022863116
...

Sheet quarterly
A1: quarter_start | B1: quarter_end | C1: rtwi | D1: tot | E1: wui_au | F1: wui_au_sm | G1: us_rgdp | H1: au_rgdp | I1: au_inf_trim | J1: au_cpi
A2: 25569 | B2: 25657 | E2: 0 | F2: 0.0111744 | G2: 5300.652 | H2: 136260 | J2: 6.69
A3: 25659 | B3: 25749 | C3: 146.45132 | D3: 59.1 | E3: 0.2192982 | F3: 0.0438596 | G3: 5308.164 | H3: 139021 | J3: 6.77
A4: 25750 | B4: 25841 | C4: 144.54268 | D4: 58.1 | E4: 0 | F4: 0.0219298 | G4: 5357.077 | H4: 138729 | J4: 6.8
A5: 25842 | B5: 25932 | C5: 145.17265 | D5: 55.6 | E5: 0.3646308 | F5: 0.0802361 | G5: 5299.672 | H5: 139332 | J5: 6.92
A6: 25934 | B6: 26022 | C6: 146.01779 | D6: 55.9 | E6: 0.655308 | F6: 0.1675247 | G6: 5443.619 | H6: 141071 | J6: 7
A7: 26024 | B7: 26114 | C7: 147.05388 | D7: 54.7 | E7: 0 | F7: 0.0776852 | G7: 5473.059 | H7: 141684 | J7: 7.11
A8: 26115 | B8: 26206 | C8: 146.56491 | D8: 55.5 | E8: 0.337344 | F8: 0.0893124 | G8: 5518.072 | H8: 146097 | J8: 7.27
A9: 26207 | B9: 26297 | C9: 147.06334 | D9: 48.6 | E9: 0.449169 | F9: 0.1235682 | G9: 5531.032 | H9: 145625 | J9: 7.42
A10: 26299 | B10: 26388 | C10: 145.50562 | D10: 51.8 | E10: 0.304909 | F10: 0.1171435 | G10: 5632.649 | H10: 143900 | J10: 7.5
A11: 26390 | B11: 26480 | C11: 144.61215 | D11: 53.9 | E11: 0 | F11: 0.0454632 | G11: 5760.47 | H11: 147105 | J11: 7.58
A12: 26481 | B12: 26572 | C12: 143.92313 | D12: 56.9 | E12: 0.373925 | F12: 0.0849486 | G12: 5814.854 | H12: 146356 | J12: 7.69
A13: 26573 | B13: 26663 | C13: 144.52606 | D13: 58 | E13: 0 | F13: 0.0373925 | G13: 5912.22 | H13: 147885 | J13: 7.77
A14: 26665 | B14: 26753 | C14: 156.0126 | D14: 66.2 | E14: 0.2447681 | F14: 0.0614178 | G14: 6058.544 | H14: 151729 | J14: 7.93
... A50: 29952 | B50: 30040 | C50: 141.04909 | D50: 50.8 | E50: 0 | F50: 0.0139587 | G50: 7295.631 | H50: 192212 | J50: 21.38
A51: 30042 | B51: 30132 | C51: 140.22066 | D51: 52.1 | E51: 0.3992547 | F51: 0.0845038 | G51: 7328.912 | H51: 193911 | I51: 2.5 | J51: 21.88
A52: 30133 | B52: 30224 | C52: 137.00849 | D52: 51.8 | E52: 0 | F52: 0.0399255 | G52: 7300.896 | H52: 192628 | I52: 2.9 | J52: 22.65
A53: 30225 | B53: 30315 | C53: 136.02815 | D53: 51.3 | E53: 0.1865324 | F53: 0.050615 | G53: 7303.817 | H53: 189523 | I53: 2.6 | J53: 23.31
A54: 30317 | B54: 30405 | C54: 132.65668 | D54: 51.6 | E54: 0.1501502 | F54: 0.0486833 | G54: 7400.066 | H54: 187708 | I54: 2.2 | J54: 23.81
A55: 30407 | B55: 30497 | C55: 125.80649 | D55: 52.2 | E55: 0 | F55: 0.0212328 | G55: 7568.456 | H55: 187314 | I55: 1.8 | J55: 24.32
A56: 30498 | B56: 30589 | C56: 129.78267 | D56: 52.1 | E56: 0 | F56: 0.005005 | G56: 7719.746 | H56: 192527 | I56: 1.5 | J56: 24.74
A57: 30590 | B57: 30680 | C57: 134.39723 | D57: 52.8 | E57: 0.1859427 | F57: 0.0371885 | G57: 7880.794 | H57: 195759 | I57: 2.1 | J57: 25.32
A58: 30682 | B58: 30771 | C58: 137.65303 | D58: 52.6 | E58: 0.1881822 | F58: 0.0562307 | G58: 8034.847 | H58: 200558 | I58: 1.4 | J58: 25.21
A59: 30773 | B59: 30863 | C59: 134.51215 | D59: 52.9 | E59: 0 | F59: 0.0250163 | G59: 8173.67 | H59: 202890 | I59: 1.5 | J59: 25.28
A60: 30864 | B60: 30955 | C60: 130.43882 | D60: 53.2 | E60: 0 | F60: 0.0062727 | G60: 8252.465 | H60: 204763 | I60: 1.2 | J60: 25.59
A61: 30956 | B61: 31046 | C61: 133.82938 | D61: 53 | E61: 0 | F61: 0 | G61: 8320.199 | H61: 205998 | I61: 1.4 | J61: 25.98
A62: 31048 | B62: 31136 | C62: 123.55459 | D62: 52.8 | E62: 0.0290158 | F62: 0.0058032 | G62: 8400.82 | H62: 209056 | I62: 1.6 | J62: 26.33
... A227: 46113 | B227: 46203 | C227: 157.31891 | D227: 94.8 | E227: 0.0850123 | F227: 0.0401574 | G227: 24269.613 | H227: 699461 | I227: 0.8 | J227: 102.31

Sheet replication_manalo_et_al
A1: quarter | B1: us_rgdp | C1: aus_tot | D1: aus_rgdp | E1: trim_inf | F1: cash_rate | G1: real_twi | H1: vix
A2: 1985Q1 | B2: 8400.82 | C2: 52.8 | D2: 209056 | E2: 1.6 | F2: 11.849437 | G2: 123.55459 | H2: NA
A3: 1985Q2 | B3: 8474.787 | C3: 49.4 | D3: 213736 | E3: 2.1 | F3: 14.926063 | G3: 109.43139 | H3: NA
A4: 1985Q3 | B4: 8604.22 | C4: 48.7 | D4: 216480 | E4: 2.1 | F4: 15.414268 | G4: 112.74262 | H4: NA
A5: 1985Q4 | B5: 8668.188 | C5: 46.6 | D5: 215854 | E5: 2.1 | F5: 17.206556 | G5: 106.52886 | H5: NA
A6: 1986Q1 | B6: 8749.127 | C6: 46.4 | D6: 217350 | E6: 2.3 | F6: 17.784504 | G6: 106.28291 | H6: NA
A7: 1986Q2 | B7: 8788.524 | C7: 46.4 | D7: 216958 | E7: 2 | F7: 13.403312 | G7: 105.42007 | H7: NA
A8: 1986Q3 | B8: 8872.601 | C8: 44.3 | D8: 217527 | E8: 2.2 | F8: 15.793683 | G8: 90.849511 | H8: NA
A9: 1986Q4 | B9: 8920.193 | C9: 44.2 | D9: 221092 | E9: 2.4 | F9: 16.053077 | G9: 95.97237 | H9: NA
A10: 1987Q1 | B10: 8986.367 | C10: 44.5 | D10: 223314 | E10: 2 | F10: 16.089727 | G10: 97.577349 | H10: NA
A11: 1987Q2 | B11: 9083.256 | C11: 45.4 | D11: 226866 | E11: 1.9 | F11: 13.559603 | G11: 101.49922 | H11: NA
A12: 1987Q3 | B12: 9162.024 | C12: 46.6 | D12: 230956 | E12: 1.6 | F12: 11.862317 | G12: 103.05213 | H12: NA
A13: 1987Q4 | B13: 9319.332 | C13: 46.7 | D13: 235600 | E13: 1.8 | F13: 10.655635 | G13: 98.611948 | H13: NA
... A21: 1989Q4 | B21: 9938.767 | C21: 55.8 | D21: 251640 | E21: 1.7 | F21: 17.837982 | G21: 117.23624 | H21: NA
A22: 1990Q1 | B22: 10047.386 | C22: 55.7 | D22: 253536 | E22: 1.7 | F22: 16.90397 | G22: 116.13691 | H22: 22.174603
A23: 1990Q2 | B23: 10083.855 | C23: 56 | D23: 253863 | E23: 1.7 | F23: 15.011762 | G23: 118.639 | H23: 18.722063
A24: 1990Q3 | B24: 10090.569 | C24: 55.4 | D24: 252550 | E24: 1.3 | F24: 14.301866 | G24: 120.72643 | H24: 25.195556
A25: 1990Q4 | B25: 9998.704 | C25: 52.7 | D25: 253941 | E25: 1.8 | F25: 13.004577 | G25: 113.32673 | H25: 26.113281
A26: 1991Q1 | B26: 9951.916 | C26: 51.9 | D26: 250758 | E26: 0.8 | F26: 12 | G26: 113.74431 | H26: 22.515833
A27: 1991Q2 | B27: 10029.51 | C27: 51.4 | D27: 250219 | E27: 1.1 | F27: 11.00942 | G27: 117.09803 | H27: 17.147031
A28: 1991Q3 | B28: 10080.195 | C28: 51.6 | D28: 251377 | E28: 1.1 | F28: 10.18254 | G28: 118.80022 | H28: 16.634219
A29: 1991Q4 | B29: 10115.329 | C29: 51 | D29: 251541 | E29: 0.7 | F29: 8.8809524 | G29: 115.73289 | H29: 17.455313
A30: 1992Q1 | B30: 10236.435 | C30: 51.2 | D30: 253547 | E30: 0.4 | F30: 7.5634921 | G30: 110.47056 | H30: 17.564286
A31: 1992Q2 | B31: 10347.429 | C31: 50.7 | D31: 255366 | E31: 0.6 | F31: 6.8809524 | G31: 111.53803 | H31: 15.616349
A32: 1992Q3 | B32: 10449.673 | C32: 49.9 | D32: 257852 | E32: 0.5 | F32: 5.8043478 | G32: 104.20373 | H32: 13.902031
A33: 1992Q4 | B33: 10558.648 | C33: 49.2 | D33: 263251 | E33: 0.5 | F33: 5.75 | G33: 101.57854 | H33: 14.761094
... A167: 2026Q2 | B167: 24269.613 | C167: 94.8 | D167: 699461 | E167: 0.8 | F167: 4.2533333 | G167: 157.31891 | H167: 18.312188
